{
  "Ada Santana Aguilera": {
    "XV": 133
  },
  "Adolfo Pérez Abellás": {
    "XIII": 16,
    "XIV": 33
  },
  "Adolfo Suárez Illana": {
    "XIII": 58,
    "XIV": 32
  },
  "Adriana Lastra Fernández": {
    "XI": 328,
    "XII": 284,
    "XIII": 29,
    "XIV": 109,
    "XV": 153
  },
  "Adriana Maldonado López": {
    "XV": 105
  },
  "Adrián Barbón Rodríguez": {
    "X": 434
  },
  "Agustín Almodóbar Barceló": {
    "XIII": 54,
    "XIV": 305
  },
  "Agustín Conde Bajén": {
    "X": 63,
    "XV": 7
  },
  "Agustín Parra Gallego": {
    "XV": 172
  },
  "Agustín Rosety Fernández de Castro": {
    "XIII": 301,
    "XIV": 255
  },
  "Agustín Santos Maraver": {
    "XV": 311
  },
  "Agustín Zamarrón Moreno": {
    "XIII": 179,
    "XIV": 19
  },
  "Aina Vidal Sáez": {
    "XI": 100,
    "XII": 256,
    "XIII": 338,
    "XIV": 266,
    "XV": 327
  },
  "Ainhoa Molina León": {
    "XV": 391
  },
  "Aitor Esteban Bravo": {
    "X": 244,
    "XI": 123,
    "XII": 235,
    "XIII": 237,
    "XIV": 94,
    "XV": 304
  },
  "Alba Soldevilla Novials": {
    "XV": 358
  },
  "Albert Botran Pahissa": {
    "XIV": 87
  },
  "Albert Rivera Díaz": {
    "XI": 227,
    "XII": 95,
    "XIII": 346
  },
  "Albert Soler Sicilia": {
    "X": 331
  },
  "Alberto Asarta Cuevas": {
    "XIV": 129,
    "XV": 316
  },
  "Alberto Casero Ávila": {
    "XIII": 136,
    "XIV": 283
  },
  "Alberto Catalán Higueras": {
    "XV": 149
  },
  "Alberto Fabra Part": {
    "XV": 108
  },
  "Alberto Garzón Espinosa": {
    "X": 70,
    "XI": 183,
    "XII": 240,
    "XIII": 334,
    "XIV": 12
  },
  "Alberto Ibáñez Mezquita": {
    "XV": 165
  },
  "Alberto Mayoral de Lamo": {
    "XV": 363
  },
  "Alberto Montero Soler": {
    "XI": 91,
    "XII": 41
  },
  "Alberto Núñez Feijóo": {
    "XV": 346
  },
  "Alberto Rodríguez Rodríguez": {
    "XI": 78,
    "XII": 328,
    "XIII": 350,
    "XIV": 338
  },
  "Alberto Rojo Blas": {
    "XV": 176
  },
  "Alberto Ruiz-Gallardón Jiménez": {
    "X": 129
  },
  "Alda Recas Martín": {
    "XV": 393
  },
  "Alejandro Alonso Núñez": {
    "X": 123
  },
  "Alejandro Fernández Álvarez": {
    "X": 279
  },
  "Alejandro García Orta": {
    "XIII": 160
  },
  "Alejandro Ramírez del Molino Morán": {
    "X": 216,
    "XI": 50,
    "XII": 120
  },
  "Alejandro Soler Mur": {
    "XIII": 142,
    "XIV": 144,
    "XV": 296
  },
  "Alexandra Fernández Gómez": {
    "XI": 274,
    "XII": 344
  },
  "Alfonso Alonso Aranegui": {
    "X": 150,
    "XI": 61,
    "XII": 308
  },
  "Alfonso Candón Adán": {
    "X": 56,
    "XI": 98,
    "XII": 77
  },
  "Alfonso Carlos Macías Gata": {
    "XV": 298
  },
  "Alfonso Guerra González": {
    "X": 76
  },
  "Alfonso Rodríguez Gómez de Celis": {
    "XIII": 196,
    "XIV": 168,
    "XV": 140
  },
  "Alfonso de Senillosa Ramoneda": {
    "X": 188
  },
  "Alfred Bosch i Pascual": {
    "X": 296
  },
  "Alfredo Prada Presa": {
    "X": 134
  },
  "Alfredo Pérez Rubalcaba": {
    "X": 301
  },
  "Alfredo Sancho Guardia": {
    "XIV": 312
  },
  "Alicia García Rodríguez": {
    "XIII": 162,
    "XIV": 50
  },
  "Alicia Piquer Sancho": {
    "XII": 377
  },
  "Alicia Ramos Jordán": {
    "XII": 374
  },
  "Alicia Sánchez-Camacho Pérez": {
    "XI": 203,
    "XII": 92
  },
  "Alicia Álvarez González": {
    "XV": 134
  },
  "Alma Alfonso Silvestre": {
    "XV": 254
  },
  "Amador Marqués Atés": {
    "XV": 79
  },
  "Amparo Botejara Sanz": {
    "XI": 60,
    "XII": 236
  },
  "Ana Belén Fernández Casero": {
    "XIII": 61,
    "XIV": 230
  },
  "Ana Belén Terrón Berbel": {
    "XI": 280,
    "XII": 174
  },
  "Ana Belén Vázquez Blanco": {
    "X": 211,
    "XII": 23,
    "XIII": 41,
    "XIV": 115,
    "XV": 196
  },
  "Ana Cobo Carmona": {
    "XV": 75
  },
  "Ana González Herdaro": {
    "XV": 407
  },
  "Ana Isabel Alós López": {
    "XI": 276,
    "XII": 201,
    "XV": 334
  },
  "Ana Marcello Santos": {
    "XI": 80,
    "XII": 338
  },
  "Ana Martínez Labella": {
    "XV": 213
  },
  "Ana María Beltrán Villalba": {
    "XIII": 222,
    "XIV": 260
  },
  "Ana María Botella Gómez": {
    "XI": 160,
    "XII": 237,
    "XIII": 127,
    "XIV": 238
  },
  "Ana María Castaño Rey": {
    "X": 416
  },
  "Ana María Madrazo Díaz": {
    "X": 109,
    "XI": 204,
    "XII": 218
  },
  "Ana María Oramas González-Moro": {
    "X": 307,
    "XI": 302,
    "XII": 94,
    "XIII": 27,
    "XIV": 161
  },
  "Ana María Pastor Julián": {
    "X": 24,
    "XI": 17,
    "XII": 10,
    "XIII": 1,
    "XIV": 31,
    "XV": 13
  },
  "Ana María Surra Spadea": {
    "XI": 320,
    "XII": 349
  },
  "Ana María Zurita Expósito": {
    "XII": 52,
    "XIII": 264,
    "XIV": 111
  },
  "Ana Mato Adrover": {
    "X": 118
  },
  "Ana Prieto Nieto": {
    "XIII": 112,
    "XIV": 81
  },
  "Ana Vanessa Rodríguez Concepción": {
    "X": 422
  },
  "Andrea Canelo Matito": {
    "XV": 388
  },
  "Andrea Fabra Fernández": {
    "X": 9
  },
  "Andrea Fernández Benéitez": {
    "XIII": 10,
    "XIV": 102,
    "XV": 31
  },
  "Andreu Martín Martínez": {
    "XV": 62
  },
  "Andrés Alberto Rodríguez Almeida": {
    "XIV": 256,
    "XV": 256
  },
  "Andrés José Ayala Sánchez": {
    "X": 29,
    "XI": 28
  },
  "Andrés Lorite Lorite": {
    "XIII": 135,
    "XIV": 105
  },
  "Andrés Núñez Jiménez": {
    "XII": 388
  },
  "Antidio Fagúndez Campo": {
    "XIV": 4,
    "XV": 29
  },
  "Antoni Picó i Azanza": {
    "X": 199
  },
  "Antoni Postius Terrado": {
    "XI": 3,
    "XII": 348
  },
  "Antoni Such Botella": {
    "X": 394
  },
  "Antonia Jover Díaz": {
    "XIII": 322,
    "XIV": 334
  },
  "Antonia López Moya": {
    "XIV": 403
  },
  "Antonio Camacho Vizcaíno": {
    "X": 299
  },
  "Antonio Cantó García del Moral": {
    "X": 282,
    "XI": 233,
    "XII": 290
  },
  "Antonio Cavacasillas Rodríguez": {
    "XV": 299
  },
  "Antonio Erias Rey": {
    "X": 97
  },
  "Antonio Gallego Burgos": {
    "X": 182
  },
  "Antonio González Terol": {
    "XI": 159,
    "XII": 170,
    "XIII": 154,
    "XIV": 166
  },
  "Antonio Gutiérrez Limones": {
    "XI": 325,
    "XII": 175
  },
  "Antonio Gutiérrez Molina": {
    "X": 21
  },
  "Antonio Gómez-Reino Varela": {
    "XI": 272,
    "XII": 346,
    "XIII": 315,
    "XIV": 176
  },
  "Antonio Hernando Vera": {
    "X": 220,
    "XI": 175,
    "XII": 259,
    "XV": 37
  },
  "Antonio Hurtado Zurera": {
    "X": 28,
    "XI": 54,
    "XII": 144,
    "XIV": 372
  },
  "Antonio Luis Amaro López": {
    "X": 420
  },
  "Antonio López Olmo": {
    "X": 431
  },
  "Antonio Martínez Gómez": {
    "XV": 102
  },
  "Antonio Pradas Torres": {
    "X": 117,
    "XI": 102,
    "XII": 148
  },
  "Antonio Pérez Insua": {
    "X": 352
  },
  "Antonio Quintana Martínez": {
    "XII": 381
  },
  "Antonio Ramón María Trevín Lombán": {
    "X": 323,
    "XI": 198,
    "XII": 216
  },
  "Antonio Rodríguez Vázquez": {
    "XI": 265
  },
  "Antonio Roldán Monés": {
    "XI": 230,
    "XII": 97,
    "XIII": 344
  },
  "Antonio Román Jasanada": {
    "X": 82,
    "XV": 59
  },
  "Antonio Salvá Verd": {
    "XIV": 162
  },
  "Antonio Vázquez Jiménez": {
    "X": 53
  },
  "Arantza Tapia Otaegi": {
    "X": 248
  },
  "Ariagona González Pérez": {
    "XIII": 198,
    "XIV": 164
  },
  "Arnau Ramírez Carner": {
    "XIII": 80,
    "XIV": 197,
    "XV": 94
  },
  "Arsenio Fernández de Mesa Díaz del Río": {
    "X": 151
  },
  "Arsenio Pacheco Atienza": {
    "X": 50
  },
  "Artemi Rallo Lombarte": {
    "XI": 90,
    "XII": 283,
    "XV": 54
  },
  "Arturo García-Tizón López": {
    "X": 22,
    "XI": 51,
    "XII": 21
  },
  "Ascensión De las Heras Ladera": {
    "X": 69
  },
  "Asier Antona Gómez": {
    "XV": 265
  },
  "Aurelio Romero Girón": {
    "X": 55
  },
  "Aurelio Zapata Simón": {
    "XIV": 397
  },
  "Aurora Nacarino-Brabo Jiménez": {
    "XIII": 172,
    "XV": 348
  },
  "Avelino De Barrionuevo Gener": {
    "XII": 4
  },
  "Baltasar Ortiz Gutiérrez": {
    "X": 429
  },
  "Bartolomé Madrid Olmo": {
    "XV": 260
  },
  "Baudilio Tomé Muguruza": {
    "X": 31
  },
  "Beatriz Jiménez Linuesa": {
    "XIV": 206,
    "XV": 41
  },
  "Beatriz Marta Escudero Berzal": {
    "X": 15,
    "XI": 16,
    "XII": 71,
    "XIII": 52
  },
  "Beatriz Micaela Carrillo de los Reyes": {
    "XIII": 8,
    "XIV": 280
  },
  "Beatriz Pino Ocampo": {
    "XIII": 126
  },
  "Beatriz Rodríguez-Salmones Cabeza": {
    "X": 212
  },
  "Beatriz Álvarez Fanjul": {
    "XIV": 101,
    "XV": 143
  },
  "Begoña García Bernal": {
    "XV": 226
  },
  "Begoña Nasarre Oliva": {
    "XIII": 189,
    "XIV": 313,
    "XV": 178
  },
  "Bella Verano Domínguez": {
    "XV": 43
  },
  "Belén Hoyo Juliá": {
    "X": 254,
    "XI": 303,
    "XII": 210,
    "XIII": 289,
    "XIV": 141,
    "XV": 67
  },
  "Bibiano Serrano Calurano": {
    "X": 180
  },
  "Bienvenido De Arriba Sánchez": {
    "XII": 13
  },
  "Bizente Serrano Izko": {
    "X": 414
  },
  "Blanca Armario González": {
    "XV": 249
  },
  "Blanca Cercas Mena": {
    "XV": 111
  },
  "Blanca Fernández Morena": {
    "XIII": 107
  },
  "Borja Sémper Pascual": {
    "XV": 258
  },
  "Candela López Tagliafico": {
    "XV": 372
  },
  "Caridad Rives Arcayna": {
    "XV": 231
  },
  "Carina Mejías Sánchez": {
    "XIII": 353,
    "XV": 331
  },
  "Carla Toscano de Balbín": {
    "XIII": 298,
    "XIV": 296,
    "XV": 295
  },
  "Carles Campuzano i Canadés": {
    "X": 219,
    "XI": 322,
    "XII": 40
  },
  "Carles Pàramo i Ponsetí": {
    "X": 163
  },
  "Carlos Alberto Sánchez Ojeda": {
    "XV": 152
  },
  "Carlos Aragonés Mendiguchía": {
    "X": 108,
    "XIV": 232,
    "XV": 259
  },
  "Carlos Casimiro Salvador Armendáriz": {
    "X": 204,
    "XI": 10,
    "XII": 27
  },
  "Carlos Enrique Muñoz Obón": {
    "X": 147
  },
  "Carlos Flores Juberías": {
    "XV": 159
  },
  "Carlos García Adanero": {
    "XIII": 161,
    "XIV": 127,
    "XV": 266
  },
  "Carlos Gil Santiago": {
    "XV": 247
  },
  "Carlos Hermoso Ayuso": {
    "XIII": 171
  },
  "Carlos Hernández Quero": {
    "XV": 345
  },
  "Carlos Hugo Fernández-Roca Suárez": {
    "XIV": 298
  },
  "Carlos Javier Floriano Corrales": {
    "X": 262,
    "XI": 130,
    "XII": 69,
    "XV": 55
  },
  "Carlos José Zambrano García-Raez": {
    "XIV": 254
  },
  "Carlos Martín Urriza": {
    "XV": 225
  },
  "Carlos Martínez Gorriarán": {
    "X": 44
  },
  "Carlos Martínez de Tejada Pérez": {
    "XIV": 407
  },
  "Carlos Pracht Ferrer": {
    "XI": 224
  },
  "Carlos Rojas García": {
    "XI": 53,
    "XII": 307,
    "XIII": 53,
    "XIV": 242,
    "XV": 12
  },
  "Carlos Simarro Vicens": {
    "XV": 402
  },
  "Carlota Merchán Mesón": {
    "XII": 356
  },
  "Carme Chacón Piqueras": {
    "X": 184,
    "XI": 290
  },
  "Carmelo Barrio Baroja": {
    "XV": 378
  },
  "Carmelo Romero Hernández": {
    "X": 59,
    "XI": 225,
    "XII": 280,
    "XIV": 241
  },
  "Carmen Andrés Añón": {
    "XIII": 79,
    "XIV": 204,
    "XV": 106
  },
  "Carmen Baños Ruiz": {
    "XII": 384,
    "XIV": 365
  },
  "Carmen Calvo Poyato": {
    "XIII": 155,
    "XIV": 258,
    "XV": 237
  },
  "Carmen Fúnez de Gregorio": {
    "XV": 65
  },
  "Carmen Martínez Ramírez": {
    "XV": 218
  },
  "Carmen Montón Giménez": {
    "X": 305
  },
  "Carmen Navarro Lacoba": {
    "XI": 207,
    "XII": 191,
    "XIII": 131,
    "XIV": 82,
    "XV": 215
  },
  "Carmen Riolobos Regadera": {
    "XIII": 20,
    "XIV": 7
  },
  "Carmen Rocío Cuello Pérez": {
    "XI": 297,
    "XII": 194
  },
  "Carmen Valido Pérez": {
    "XII": 149
  },
  "Carolina Bescansa Hernández": {
    "XI": 294,
    "XII": 258
  },
  "Carolina España Reina": {
    "X": 235,
    "XI": 20,
    "XII": 15,
    "XIII": 220,
    "XIV": 316
  },
  "Carolina Telechea i Lozano": {
    "XII": 375,
    "XIII": 253,
    "XIV": 188
  },
  "Cayetana Álvarez de Toledo Peralta Ramos": {
    "X": 312
  },
  "Cayetana Álvarez de Toledo Peralta-Ramos": {
    "XIII": 327,
    "XIV": 308,
    "XV": 315
  },
  "Cayo Lara Moya": {
    "X": 72
  },
  "Celia Alberto Pérez": {
    "X": 173,
    "XII": 359
  },
  "Celia Villalobos Talero": {
    "X": 233,
    "XI": 14,
    "XII": 14
  },
  "Celinda Sánchez García": {
    "X": 67
  },
  "Celso Luis Delgado Arce": {
    "X": 265,
    "XI": 36,
    "XII": 20,
    "XIII": 42,
    "XIV": 116,
    "XV": 32
  },
  "Chesús Yuste Cabello": {
    "X": 71
  },
  "Ciprià Císcar Casabán": {
    "X": 329,
    "XII": 351
  },
  "Concep Cañadell Salvia": {
    "XIV": 21
  },
  "Concepció Veray Cama": {
    "X": 274
  },
  "Concepción Gamarra Ruiz-Clavijo": {
    "XIII": 294,
    "XIV": 261,
    "XV": 314
  },
  "Concepción González Gutiérrez": {
    "X": 366
  },
  "Conrado Escobar Las Heras": {
    "X": 84
  },
  "Cristina Abades Martínez": {
    "XV": 160
  },
  "Cristina Agüera Gago": {
    "XV": 136
  },
  "Cristina Alicia Esteban Calonje": {
    "XIII": 285,
    "XIV": 297
  },
  "Cristina López Zamora": {
    "XIII": 352,
    "XIV": 224,
    "XV": 365
  },
  "Cristina Moreno Borrás": {
    "XV": 385
  },
  "Cristina Narbona Ruiz": {
    "X": 203,
    "XV": 271
  },
  "Cristina Teniente Sánchez": {
    "XV": 47
  },
  "Cristina Valido García": {
    "XV": 38
  },
  "Cristóbal Garre Murcia": {
    "XV": 84
  },
  "Cristóbal Ricardo Montoro Romero": {
    "X": 27,
    "XI": 243,
    "XII": 200
  },
  "César Joaquín Ramos Esteban": {
    "XI": 108,
    "XII": 70,
    "XIII": 57,
    "XIV": 178,
    "XV": 100
  },
  "César Luena López": {
    "X": 90,
    "XI": 292,
    "XII": 119
  },
  "César Sánchez Pérez": {
    "XIII": 85,
    "XIV": 249,
    "XV": 217
  },
  "Daniel Fernández González": {
    "X": 333
  },
  "Daniel Pérez Osma": {
    "XV": 16
  },
  "Daniel Senderos Oraá": {
    "XIV": 367,
    "XV": 17
  },
  "Daniel Serrano Coronado": {
    "X": 181
  },
  "Daniel Vicente Viondi": {
    "XIII": 99,
    "XIV": 80
  },
  "David Bravo Bueno": {
    "XI": 74
  },
  "David Bruzos Higuero": {
    "XI": 142
  },
  "David García Gomis": {
    "XV": 104
  },
  "David Regades Fernández": {
    "XV": 135
  },
  "David Serrada Pariente": {
    "XI": 9,
    "XII": 168,
    "XIII": 109,
    "XIV": 37,
    "XV": 24
  },
  "Diana Morant Ripoll": {
    "XV": 278
  },
  "Diego Cañamero Valle": {
    "XII": 298
  },
  "Diego Clemente Giménez": {
    "XI": 97,
    "XII": 135
  },
  "Diego Gago Bugarín": {
    "XIII": 290,
    "XIV": 121
  },
  "Diego López Garrido": {
    "X": 328
  },
  "Diego Movellán Lombilla": {
    "XII": 365,
    "XIII": 7,
    "XIV": 78
  },
  "Diego Taibo Monelos": {
    "XIV": 373
  },
  "Dolores Delgado García": {
    "XIII": 32,
    "XIV": 262
  },
  "Dolors Montserrat Montserrat": {
    "X": 273,
    "XI": 239,
    "XII": 83
  },
  "Dolors Terradas Viñals": {
    "XI": 104
  },
  "Domingo Lorenzo Rodríguez": {
    "XI": 190,
    "XII": 202
  },
  "Edmundo Bal Francés": {
    "XIII": 45,
    "XIV": 211
  },
  "Eduard Pujol Bonell": {
    "XV": 240
  },
  "Eduardo Calvo García": {
    "XIII": 236
  },
  "Eduardo Carazo Hermoso": {
    "XIV": 245,
    "XV": 282
  },
  "Eduardo Fernández García": {
    "X": 298,
    "XI": 26,
    "XII": 87
  },
  "Eduardo Javier Maura Zorita": {
    "XI": 144,
    "XII": 188
  },
  "Eduardo Luis Ruiz Navarro": {
    "XIV": 217
  },
  "Eduardo Madina Muñoz": {
    "X": 239,
    "XII": 112
  },
  "Eduardo Santos Itoiz": {
    "XI": 64,
    "XII": 323
  },
  "Edurne Uriarte Bengoechea": {
    "XIII": 36,
    "XIV": 30,
    "XV": 374
  },
  "Elena Castillo López": {
    "XIV": 77
  },
  "Elena Faba de la Encarnación": {
    "XI": 251,
    "XII": 275
  },
  "Elena María Bastidas Bono": {
    "XI": 169,
    "XII": 64
  },
  "Elena Máñez Rodríguez": {
    "XIII": 274,
    "XIV": 284
  },
  "Elena Ribera i Garijo": {
    "XI": 2
  },
  "Elena Valenciano Martínez-Orozco": {
    "X": 135
  },
  "Elisa Garrido Jiménez": {
    "XV": 116
  },
  "Eloi Badia Casas": {
    "XV": 329
  },
  "Eloy Suárez Lamata": {
    "X": 32,
    "XI": 33,
    "XII": 18,
    "XIII": 26,
    "XIV": 214
  },
  "Eloísa María Cabrera Carmona": {
    "XII": 45
  },
  "Elvira Ramón Utrabo": {
    "X": 77,
    "XI": 314,
    "XII": 179,
    "XIII": 119,
    "XIV": 8
  },
  "Elvira Velasco Morillo": {
    "XIII": 354,
    "XIV": 10,
    "XV": 34
  },
  "Elías Bendodo Benasayag": {
    "XV": 209
  },
  "Emilia Almodóvar Sánchez": {
    "XV": 367
  },
  "Emilio Del Río Sanz": {
    "XI": 47,
    "XII": 74
  },
  "Emilio Jesús Del Valle Rodríguez": {
    "XIV": 175,
    "XV": 124
  },
  "Emilio Olabarría Muñoz": {
    "X": 247
  },
  "Emilio Sáez Cruz": {
    "XV": 138
  },
  "Encarnación Jiménez Mínguez": {
    "X": 363
  },
  "Engracia Rivera Arias": {
    "XV": 157
  },
  "Enric Bataller i Ruiz": {
    "XI": 286,
    "XII": 225
  },
  "Enrique Belda Pérez-Pedrero": {
    "XV": 208
  },
  "Enrique Bueno Prado": {
    "XI": 194
  },
  "Enrique Fajarnés Ribas": {
    "X": 6
  },
  "Enrique Fernando Santiago Romero": {
    "XIII": 24,
    "XIV": 45,
    "XV": 125
  },
  "Enrique Luis Martín Rodríguez": {
    "X": 361
  },
  "Enrique Víctor Rivero Ortega": {
    "XIII": 168
  },
  "Enrique Álvarez Sostres": {
    "X": 226
  },
  "Ernesto Aguiar Rodríguez": {
    "X": 171,
    "XII": 7
  },
  "Esperanza Reynal Reillo": {
    "XV": 246
  },
  "Esperança Esteve Ortega": {
    "X": 344
  },
  "Esteban González Pons": {
    "X": 318,
    "XV": 66
  },
  "Ester Capella i Farré": {
    "XI": 278,
    "XII": 301
  },
  "Ester Muñoz de la Iglesia": {
    "XV": 28
  },
  "Esther Gil de Reboleño Lastortres": {
    "XV": 86
  },
  "Esther Llamazares Domingo": {
    "XV": 340
  },
  "Esther Padilla Ruiz": {
    "XIII": 65,
    "XIV": 173
  },
  "Esther Peña Camarero": {
    "XI": 122,
    "XII": 303,
    "XIII": 186,
    "XIV": 18,
    "XV": 95
  },
  "Esther Rodríguez Suárez": {
    "XV": 359
  },
  "Etna Estrems Fayos": {
    "XV": 392
  },
  "Eugenio Nasarre Goicoechea": {
    "X": 267
  },
  "Eva Bravo Barco": {
    "XIII": 281,
    "XIV": 281
  },
  "Eva Durán Ramos": {
    "X": 160
  },
  "Eva García Sempere": {
    "XII": 241,
    "XIII": 335
  },
  "Eva Patricia Bueno Campanario": {
    "XIII": 345,
    "XIV": 314
  },
  "Evarist Aznar Teruel": {
    "XV": 406
  },
  "Ezequiel García Nieto": {
    "XIV": 398
  },
  "Federico Buyolo García": {
    "X": 92
  },
  "Federico Cabello de Alba Hernández": {
    "X": 105
  },
  "Federico Trillo-Figueroa Martínez-Conde": {
    "X": 229
  },
  "Felipe Jesús Sicilia Alférez": {
    "X": 122,
    "XI": 12,
    "XII": 107,
    "XIII": 202,
    "XIV": 259
  },
  "Feliu-Joan Guillaumes i Ràfols": {
    "X": 319,
    "XII": 367
  },
  "Fernando Adolfo Gutiérrez Díaz de Otazu": {
    "XIII": 31,
    "XIV": 149
  },
  "Fernando De Páramo Gómez": {
    "XIII": 284
  },
  "Fernando De Rosa Torner": {
    "XV": 248
  },
  "Fernando Grande-Marlaska Gómez": {
    "XIII": 271,
    "XIV": 182,
    "XV": 286
  },
  "Fernando Iglesias García": {
    "XI": 147
  },
  "Fernando López-Amor García": {
    "X": 94
  },
  "Fernando Martínez-Maillo Toribio": {
    "XI": 106
  },
  "Fernando Martínez-Maíllo Toribio": {
    "XII": 32
  },
  "Fernando Maura Barandiarán": {
    "XI": 176,
    "XII": 209
  },
  "Fernando Navarro Fernández-Rodríguez": {
    "XI": 185,
    "XII": 25
  },
  "Ferran Bel Accensi": {
    "XI": 307,
    "XII": 294,
    "XIV": 14
  },
  "Ferran Verdejo Vicente": {
    "XV": 23
  },
  "Fidel Prieto Romero": {
    "XI": 250
  },
  "Francesc Homs Molist": {
    "XI": 256,
    "XII": 39
  },
  "Francesc Vallès Vives": {
    "X": 158
  },
  "Francesc Xavier Domènech Sampere": {
    "XI": 138,
    "XII": 268
  },
  "Francesc Xavier Eritja Ciuró": {
    "XI": 345,
    "XII": 331,
    "XIII": 256,
    "XIV": 186
  },
  "Francesc-Marc Álvaro Vidal": {
    "XV": 222
  },
  "Francina Armengol Socias": {
    "XV": 185
  },
  "Francisco Aranda Vargas": {
    "XIII": 77,
    "XIV": 198,
    "XV": 21
  },
  "Francisco De la Torre Díaz": {
    "XI": 309,
    "XII": 59,
    "XIII": 129
  },
  "Francisco Domingo Cabrera García": {
    "X": 176,
    "XI": 351
  },
  "Francisco González Cabaña": {
    "X": 114
  },
  "Francisco Hernández Spínola": {
    "XI": 327
  },
  "Francisco Igea Arisqueta": {
    "XI": 67,
    "XII": 9
  },
  "Francisco Javier Cano Leal": {
    "XI": 254,
    "XII": 117,
    "XIII": 166
  },
  "Francisco Javier Fernández-Bravo García": {
    "XIII": 115
  },
  "Francisco Javier Hervías Chirosa": {
    "XI": 264,
    "XIII": 225
  },
  "Francisco Javier Ortega Smith-Molina": {
    "XIII": 296,
    "XIV": 326,
    "XV": 325
  },
  "Francisco José Alcaraz Martos": {
    "XIV": 252,
    "XV": 4
  },
  "Francisco José Conde López": {
    "XV": 349
  },
  "Francisco José Contreras Peláez": {
    "XIV": 229
  },
  "Francisco José Salazar Rodríguez": {
    "XIII": 38,
    "XIV": 5,
    "XV": 126
  },
  "Francisco Lucas Ayala": {
    "XV": 230
  },
  "Francisco Manuel Caamaño Domínguez": {
    "X": 66
  },
  "Francisco Martín Bernabé Pérez": {
    "XII": 67
  },
  "Francisco Martínez Vázquez": {
    "XII": 282
  },
  "Francisco Molinero Hoyos": {
    "X": 48,
    "XI": 208,
    "XII": 109
  },
  "Francisco Márquez de la Rubia": {
    "X": 196
  },
  "Francisco Polo Llavata": {
    "XIII": 75,
    "XIV": 201
  },
  "Francisco Sierra Caballero": {
    "XV": 268
  },
  "Francisco Vañó Ferre": {
    "X": 52,
    "XII": 387
  },
  "Francisco Xesús Jorquera Caselas": {
    "X": 290
  },
  "Fuensanta Lima Cid": {
    "XIII": 17,
    "XIV": 59
  },
  "Fèlix Alonso Cantorné": {
    "XV": 269
  },
  "Félix Alonso Cantorné": {
    "XI": 88,
    "XII": 247
  },
  "Félix Bolaños García": {
    "XV": 253
  },
  "Félix De las Cuevas Cortés": {
    "XV": 107
  },
  "Félix Lavilla Martínez": {
    "X": 103
  },
  "Félix Álvarez Palleiro": {
    "XII": 132
  },
  "Gabino Puche Rodríguez-Acosta": {
    "X": 39
  },
  "Gabriel Blanco Arrúe": {
    "XV": 400
  },
  "Gabriel Cruz Santana": {
    "XV": 168
  },
  "Gabriel Echávarri Fernández": {
    "X": 89
  },
  "Gabriel Elorriaga Pisarik": {
    "X": 73,
    "XIV": 376
  },
  "Gabriel Rufián Romero": {
    "XI": 340,
    "XII": 335,
    "XIII": 252,
    "XIV": 187,
    "XV": 312
  },
  "Gala Pin Ferrando": {
    "XV": 330
  },
  "Gaspar Carlos Zarrías Arévalo": {
    "X": 186
  },
  "Gaspar Llamazares Trigo": {
    "X": 228
  },
  "Gema Conde Martínez": {
    "X": 14
  },
  "Gema López Somoza": {
    "XII": 378,
    "XIV": 363
  },
  "Gemma Araujo Morales": {
    "XIV": 364
  },
  "Genís Boadella Esteve": {
    "XIV": 24
  },
  "Georgina Trías Gil": {
    "XIV": 277
  },
  "Gerard Gómez del Moral Fuster": {
    "XIII": 336
  },
  "Gerard Álvarez i García": {
    "XIV": 384
  },
  "Gerardo Camps Devesa": {
    "X": 315,
    "XI": 301,
    "XII": 156
  },
  "Gerardo Pisarello Prados": {
    "XIII": 199,
    "XIV": 290,
    "XV": 328
  },
  "Germán Augusto López Iglesias": {
    "X": 179
  },
  "Germán Renau Martínez": {
    "XIII": 214,
    "XIV": 52
  },
  "Germán Rodríguez Sánchez": {
    "X": 378,
    "XI": 300
  },
  "Gonzalo José Ordóñez Puime": {
    "X": 400
  },
  "Gonzalo Palacín Guarné": {
    "XI": 158,
    "XII": 321
  },
  "Gonzalo Redondo Cárdenas": {
    "XV": 98
  },
  "Gonzalo Robles Orozco": {
    "X": 33
  },
  "Gracia Fernández Moya": {
    "X": 365
  },
  "Gregorio Cámara Villar": {
    "XI": 268,
    "XII": 278
  },
  "Guillem García Gasulla": {
    "X": 142
  },
  "Guillermo Antonio Meijón Couselo": {
    "X": 153,
    "XI": 180,
    "XII": 162,
    "XIII": 74,
    "XIV": 1
  },
  "Guillermo Collarte Rodríguez": {
    "X": 283
  },
  "Guillermo Díaz Gómez": {
    "XII": 133,
    "XIII": 176,
    "XIV": 122
  },
  "Guillermo Hita Téllez": {
    "XV": 381
  },
  "Guillermo Mariscal Anaya": {
    "X": 174,
    "XI": 334,
    "XII": 319,
    "XIII": 113,
    "XIV": 339,
    "XV": 255
  },
  "Hana Jalloul Muro": {
    "XV": 356
  },
  "Helena Caballero Gutiérrez": {
    "XIII": 30,
    "XIV": 320
  },
  "Helena Castellano Ramón": {
    "X": 213
  },
  "Herick Manuel Campos Arteseros": {
    "X": 222,
    "XI": 199,
    "XII": 372
  },
  "Herminio Rufino Sancho Íñiguez": {
    "XIII": 157,
    "XIV": 15,
    "XV": 130
  },
  "Héctor Gómez Hernández": {
    "XIII": 232,
    "XIV": 104,
    "XV": 302
  },
  "Héctor Illueca Ballester": {
    "XIII": 243,
    "XIV": 170
  },
  "Héctor Palencia Rubio": {
    "XV": 1
  },
  "Idoia Sagastizabal Unzetabarrenetxea": {
    "XII": 364,
    "XIII": 233,
    "XIV": 98,
    "XV": 309
  },
  "Ignacio Astarloa Huarte-Mendicoa": {
    "X": 243
  },
  "Ignacio Cosidó Gutiérrez": {
    "X": 140
  },
  "Ignacio Garriga Vaz de Concicao": {
    "XIII": 302,
    "XIV": 150
  },
  "Ignacio Gil Lázaro": {
    "X": 325,
    "XIII": 299,
    "XIV": 295,
    "XV": 117
  },
  "Ignacio Hoces Íñiguez": {
    "XV": 194
  },
  "Ignacio López Cano": {
    "XIII": 51,
    "XIV": 343,
    "XV": 264
  },
  "Ignacio Magaña Sierra": {
    "X": 418
  },
  "Ignacio Tremiño Gómez": {
    "XII": 48
  },
  "Ignacio Uriarte Ayala": {
    "X": 255
  },
  "Ignacio Urquizu Sancho": {
    "XI": 25,
    "XII": 75
  },
  "Ignasi Candela Serna": {
    "XI": 284,
    "XII": 224
  },
  "Ignasi Conesa Coma": {
    "XV": 352
  },
  "Iker Urbina Fernández": {
    "X": 337
  },
  "Ildefonso R. Pastor González": {
    "X": 358
  },
  "Indalecio Gutiérrez Salinas": {
    "XIV": 358
  },
  "Inmaculada Guaita Vañó": {
    "X": 391
  },
  "Inmaculada Riera i Reñé": {
    "X": 198
  },
  "Inmaculada Rodríguez-Piñero Fernández": {
    "X": 272
  },
  "Inés Arrimadas García": {
    "XIII": 276,
    "XIV": 331
  },
  "Inés Granollers Cunillera": {
    "XIII": 257,
    "XIV": 183,
    "XV": 221
  },
  "Inés María Cañizares Pacheco": {
    "XIV": 152
  },
  "Inés Plaza García": {
    "XV": 81
  },
  "Inés Sabanés Nadal": {
    "XIV": 234
  },
  "Ione Belarra Urteaga": {
    "XI": 93,
    "XII": 181,
    "XIII": 138,
    "XIV": 139,
    "XV": 262
  },
  "Irene Garrido Valenzuela": {
    "X": 138,
    "XI": 18,
    "XII": 11,
    "XV": 42
  },
  "Irene Jódar Pérez": {
    "XV": 405
  },
  "Irene Lozano Domingo": {
    "X": 43,
    "XI": 313
  },
  "Irene María Montero Gil": {
    "XI": 154,
    "XII": 154,
    "XIII": 212,
    "XIV": 329
  },
  "Irene Moreno Felipe": {
    "X": 356
  },
  "Irene Rivera Andrés": {
    "XI": 258,
    "XII": 245,
    "XIII": 248
  },
  "Isabel Cabezas Regaño": {
    "XII": 362
  },
  "Isabel Celaá Diéguez": {
    "XIII": 272,
    "XIV": 299
  },
  "Isabel Franco Carmona": {
    "XI": 92,
    "XII": 195,
    "XIII": 246,
    "XIV": 321
  },
  "Isabel García Tejerina": {
    "XI": 347,
    "XII": 316,
    "XIII": 343,
    "XIV": 323
  },
  "Isabel Gema Pérez Recuerda": {
    "XIV": 395,
    "XV": 88
  },
  "Isabel Iniesta Egido": {
    "XV": 137
  },
  "Isabel López i Chamosa": {
    "X": 215
  },
  "Isabel María Borrego Cortés": {
    "X": 18,
    "XI": 29,
    "XII": 91,
    "XIII": 89,
    "XIV": 130,
    "XV": 145
  },
  "Isabel María Pérez Ortiz": {
    "XV": 8
  },
  "Isabel Pozueta Fernández": {
    "XIV": 65,
    "XV": 288
  },
  "Isabel Rodríguez García": {
    "X": 292,
    "XI": 196,
    "XII": 246,
    "XV": 97
  },
  "Isabel Sánchez Robles": {
    "X": 379
  },
  "Isaura Leal Fernández": {
    "XIII": 98,
    "XIV": 352,
    "XV": 191
  },
  "Isidre Gavin i Valls": {
    "XV": 239
  },
  "Isidro Manuel Martínez Oblanca": {
    "XI": 49,
    "XII": 151,
    "XIV": 20
  },
  "Ismael Cortés Gómez": {
    "XIII": 164,
    "XIV": 350
  },
  "Iván Cacho Isla": {
    "XV": 401
  },
  "Iván Espinosa de los Monteros de Simón": {
    "XIII": 270,
    "XIV": 83
  },
  "Iñaki Antigüedad Auzmendi": {
    "X": 342
  },
  "Iñaki Ruiz de Pinedo Undiano": {
    "XIII": 211,
    "XIV": 64,
    "XV": 289
  },
  "Jacobo González-Robatto Perote": {
    "XV": 121
  },
  "Jaime Eduardo de Olano Vela": {
    "X": 280,
    "XI": 114,
    "XII": 152,
    "XIII": 159,
    "XIV": 167,
    "XV": 161
  },
  "Jaime García-Legaz Ponce": {
    "X": 308
  },
  "Jaime Javier Barrero López": {
    "X": 20
  },
  "Jaime Miguel De los Santos González": {
    "XV": 270
  },
  "Jaime Miguel Mateu Istúriz": {
    "XI": 86,
    "XII": 2,
    "XIV": 133
  },
  "Jaume Alonso-Cuevillas i Sayrol": {
    "XIII": 279,
    "XIV": 26
  },
  "Jaume Asens Llodrà": {
    "XIII": 200,
    "XIV": 291
  },
  "Jaume Moya Matas": {
    "XI": 103,
    "XII": 267
  },
  "Javier Alfonso Cendón": {
    "XIII": 11,
    "XIV": 103,
    "XV": 252
  },
  "Javier Antón Cacho": {
    "XI": 57,
    "XII": 198,
    "XIII": 60,
    "XIV": 100
  },
  "Javier Aureliano García Molina": {
    "XIII": 39
  },
  "Javier Bas Corugeira": {
    "XIV": 118
  },
  "Javier Calvente Gallego": {
    "XII": 358
  },
  "Javier Celaya Brey": {
    "XV": 162
  },
  "Javier Cerqueiro González": {
    "XIV": 47
  },
  "Javier De Andrés Guerra": {
    "XV": 205
  },
  "Javier José Folch Blanc": {
    "XV": 115
  },
  "Javier Maroto Aranzábal": {
    "XII": 355
  },
  "Javier Merino Martínez": {
    "XIV": 138,
    "XV": 99
  },
  "Javier Noriega Gómez": {
    "XV": 141
  },
  "Javier Puente Redondo": {
    "X": 359
  },
  "Javier Rodríguez Palacios": {
    "XV": 355
  },
  "Javier Ruano García": {
    "XII": 363
  },
  "Javier Sánchez Serna": {
    "XI": 75,
    "XII": 163,
    "XIII": 221,
    "XIV": 67,
    "XV": 292
  },
  "Jesús Caicedo Bernabé": {
    "X": 8
  },
  "Jesús Caldera Sánchez-Capitán": {
    "X": 79
  },
  "Jesús Ignacio Vázquez García": {
    "X": 404
  },
  "Jesús María Fernández Díaz": {
    "XI": 257,
    "XII": 244
  },
  "Jesús Mayoral Pérez": {
    "XV": 366
  },
  "Jesús Posada Moreno": {
    "X": 57,
    "XI": 23,
    "XII": 118
  },
  "Jesús Postigo Quintana": {
    "XII": 72,
    "XIV": 51
  },
  "Jesús Ruiz López": {
    "XIV": 404
  },
  "Jimena Delgado-Taramona Hernández": {
    "XV": 235
  },
  "Joan Baldoví Roda": {
    "X": 275,
    "XI": 281,
    "XII": 223,
    "XIII": 340,
    "XIV": 247
  },
  "Joan Canongia Gerona": {
    "X": 383
  },
  "Joan Capdevila i Esteve": {
    "XI": 323,
    "XII": 336,
    "XIII": 255,
    "XIV": 172
  },
  "Joan Coscubiela Conesa": {
    "X": 202
  },
  "Joan Josep Nuet Pujals": {
    "X": 227,
    "XIII": 263,
    "XIV": 189
  },
  "Joan Margall Sastre": {
    "XII": 376,
    "XIII": 260,
    "XIV": 193
  },
  "Joan Mena Arca": {
    "XI": 101,
    "XII": 253,
    "XIII": 156,
    "XIV": 264
  },
  "Joan Mesquida Ferrando": {
    "XIII": 18
  },
  "Joan Mesquida Mayans": {
    "XV": 132
  },
  "Joan Olòriz Serra": {
    "XI": 319,
    "XII": 332
  },
  "Joan Rangel Tarrés": {
    "X": 240
  },
  "Joan Ruiz i Carbonell": {
    "X": 143,
    "XI": 306,
    "XII": 261,
    "XIII": 81,
    "XIV": 209
  },
  "Joan Tardà i Coma": {
    "X": 295,
    "XI": 321,
    "XII": 334
  },
  "Joaquín Albaladejo Martínez": {
    "XI": 85,
    "XII": 255
  },
  "Joaquín Francisco Puig Ferrer": {
    "X": 17
  },
  "Joaquín Martínez Salmerón": {
    "XIV": 405,
    "XV": 182
  },
  "Joaquín María García Díez": {
    "X": 167,
    "XI": 156,
    "XII": 324,
    "XIII": 158,
    "XIV": 11
  },
  "Joaquín Melgarejo Moreno": {
    "XV": 211
  },
  "Joaquín Moreno Latorre": {
    "XIII": 182
  },
  "Joaquín Robles López": {
    "XIII": 293,
    "XIV": 246,
    "XV": 318
  },
  "Joaquín Villanova Rueda": {
    "X": 234
  },
  "Jon Iñarritu García": {
    "X": 338,
    "XIII": 209,
    "XIV": 62,
    "XV": 290
  },
  "Jonay Quintero Hernández": {
    "XV": 394
  },
  "Jordi Jané i Guasch": {
    "X": 192
  },
  "Jordi Roca Mas": {
    "XI": 304,
    "XII": 106
  },
  "Jordi Salvador i Duch": {
    "XI": 341,
    "XII": 337,
    "XIII": 337,
    "XIV": 184,
    "XV": 77
  },
  "Jordi Sánchez Picanyol": {
    "XIII": 331
  },
  "Jordi Turull Negre": {
    "XIII": 330
  },
  "Jordi Xuclà i Costa": {
    "X": 162,
    "XI": 1,
    "XII": 6
  },
  "Jorge Campos Asensi": {
    "XV": 207
  },
  "Jorge Fernández Díaz": {
    "X": 304,
    "XI": 140,
    "XII": 169
  },
  "Jorge Luis Bail": {
    "XI": 19,
    "XII": 60
  },
  "Jorge Moragas Sánchez": {
    "X": 346,
    "XI": 344,
    "XII": 312
  },
  "Jorge Pueyo Sanz": {
    "XV": 201
  },
  "Jorge Roselló Bouso": {
    "XIV": 406
  },
  "Joseba Andoni Agirretxea Urresti": {
    "X": 380,
    "XI": 119,
    "XII": 233,
    "XIII": 234,
    "XIV": 99,
    "XV": 305
  },
  "Josefa Andrés Barea": {
    "XIII": 120,
    "XIV": 66
  },
  "Josefa Inmaculada González Bayo": {
    "XI": 270,
    "XII": 192
  },
  "Josep Antoni Duran i Lleida": {
    "X": 194
  },
  "Josep Antoni Santamaría i Mateo": {
    "X": 427
  },
  "Josep Lluís Grau Valles": {
    "X": 415
  },
  "Josep Maria Cervera Pinart": {
    "XV": 242
  },
  "Josep Maria Cruset Domènech": {
    "XV": 244
  },
  "Josep Pagès i Massó": {
    "XIV": 379,
    "XV": 389
  },
  "Josep Paré Aregall": {
    "XV": 369
  },
  "Josep Pérez Moya": {
    "X": 411
  },
  "Josep Rull Andreu": {
    "XIII": 332
  },
  "Josep Sánchez i Llibre": {
    "X": 195
  },
  "Josep Vendrell Gardeñes": {
    "XI": 96,
    "XII": 250
  },
  "Josu Iñaki Erkoreka Gervasio": {
    "X": 246
  },
  "Josune Gorospe Elezcano": {
    "XIII": 235,
    "XIV": 96
  },
  "José Alberto Herrero Bono": {
    "X": 398,
    "XI": 39,
    "XII": 184,
    "XIII": 68,
    "XIV": 239,
    "XV": 277
  },
  "José Alberto Martín-Toledano Suárez": {
    "X": 259,
    "XI": 155,
    "XII": 104
  },
  "José Andrés Torres Mora": {
    "X": 38,
    "XI": 248,
    "XII": 158
  },
  "José Antonio Alonso Suárez": {
    "X": 187
  },
  "José Antonio Bartolomé Cachón": {
    "XIII": 170
  },
  "José Antonio Bermúdez de Castro Fernández": {
    "X": 326,
    "XI": 311,
    "XII": 311,
    "XIII": 282,
    "XIV": 181,
    "XV": 118
  },
  "José Antonio Calle Fuentes": {
    "XI": 195
  },
  "José Antonio Mirón Canelo": {
    "XIII": 167
  },
  "José Antonio Montilla Martos": {
    "XIII": 147,
    "XIV": 194
  },
  "José Antonio Nieto Ballesteros": {
    "XI": 235,
    "XII": 189
  },
  "José Antonio Rodríguez Salas": {
    "XIII": 207,
    "XIV": 6,
    "XV": 128
  },
  "José Antonio Viera Chacón": {
    "X": 116
  },
  "José Blanco López": {
    "X": 96
  },
  "José Cano Fuster": {
    "XI": 188,
    "XII": 63
  },
  "José Carlos Durán Peralta": {
    "XIII": 13,
    "XIV": 342
  },
  "José Carlos Díaz Rodríguez": {
    "XIV": 389
  },
  "José Cruz Pérez Lapazarán": {
    "X": 224
  },
  "José David Carracedo Verde": {
    "XII": 318
  },
  "José Enrique Fernández de Moya Romero": {
    "XI": 133,
    "XII": 126
  },
  "José Enrique Núñez Guijarro": {
    "XV": 373
  },
  "José Enrique Serrano Martínez": {
    "X": 324,
    "XII": 369
  },
  "José Eugenio Azpiroz Villar": {
    "X": 276
  },
  "José Francisco Duque Morán": {
    "XIV": 401
  },
  "José Guirao Cabrera": {
    "XIII": 250,
    "XIV": 216
  },
  "José Ignacio Echániz Salgado": {
    "XI": 279,
    "XII": 146,
    "XIII": 325,
    "XIV": 89
  },
  "José Ignacio Landaluce Calleja": {
    "X": 166
  },
  "José Ignacio Llorens Torres": {
    "X": 251,
    "XII": 110
  },
  "José Ignacio Prendes Prendes": {
    "XI": 249,
    "XII": 302,
    "XIII": 347
  },
  "José Ignacio Romaní Cantera": {
    "XII": 393,
    "XIV": 396,
    "XV": 308
  },
  "José Ignacio Sánchez Amor": {
    "X": 306,
    "XI": 166,
    "XII": 197
  },
  "José Jaime Alonso Díaz-Guerra": {
    "XII": 22
  },
  "José Javier Izquierdo Roncero": {
    "XIII": 12,
    "XIV": 156
  },
  "José Javier Lasarte Iribarren": {
    "XI": 247,
    "XII": 35
  },
  "José Juan Díaz Trillo": {
    "XI": 186,
    "XII": 273
  },
  "José Juan Sánchez Barrera": {
    "X": 373
  },
  "José Losada Fernández": {
    "XIV": 353,
    "XV": 353
  },
  "José Luis Aceves Galindo": {
    "XIII": 83,
    "XIV": 56,
    "XV": 64
  },
  "José Luis Ayllón Manso": {
    "X": 217,
    "XI": 260,
    "XII": 286
  },
  "José Luis Bueno Pinto": {
    "XIV": 392
  },
  "José Luis Centella Gómez": {
    "X": 23
  },
  "José Luis Martínez González": {
    "XI": 238,
    "XII": 115,
    "XIII": 144
  },
  "José Luis Ramos Rodríguez": {
    "XIII": 35,
    "XIV": 218
  },
  "José Luis Ábalos Meco": {
    "X": 268,
    "XI": 162,
    "XII": 171,
    "XIII": 59,
    "XIV": 267,
    "XV": 127
  },
  "José López Garrido": {
    "X": 284
  },
  "José Manuel Albares Bueno": {
    "XV": 275
  },
  "José Manuel Franco Pardo": {
    "XIII": 95,
    "XIV": 120
  },
  "José Manuel García-Margallo y Marfil": {
    "XI": 44,
    "XII": 180
  },
  "José Manuel Girela de la Fuente": {
    "X": 397,
    "XI": 298
  },
  "José Manuel Soria López": {
    "X": 168,
    "XI": 246
  },
  "José Manuel Velasco Retamosa": {
    "XV": 184
  },
  "José Manuel Villegas Pérez": {
    "XI": 234,
    "XII": 100,
    "XIII": 224
  },
  "José Martínez Olmos": {
    "X": 285
  },
  "José María Alonso Ruiz": {
    "X": 225
  },
  "José María Barreda Fontes": {
    "X": 293,
    "XI": 181,
    "XII": 68
  },
  "José María Barrios Tejero": {
    "XI": 37,
    "XII": 33
  },
  "José María Benegas Haddad": {
    "X": 310
  },
  "José María Beneyto Pérez": {
    "X": 93
  },
  "José María Chiquillo Barber": {
    "XI": 163,
    "XII": 254
  },
  "José María Eiros Bouza": {
    "XI": 63
  },
  "José María Espejo-Saavedra Conesa": {
    "XIII": 185,
    "XIV": 257
  },
  "José María Figaredo Álvarez-Sala": {
    "XIII": 273,
    "XIV": 318,
    "XV": 193
  },
  "José María García Urbano": {
    "XI": 339
  },
  "José María Lassalle Ruiz": {
    "X": 85,
    "XI": 212,
    "XII": 81
  },
  "José María Mazón Ramos": {
    "XIII": 71,
    "XIV": 349
  },
  "José María Sánchez García": {
    "XIV": 322,
    "XV": 53
  },
  "José Miguel Camacho Sánchez": {
    "XI": 201,
    "XII": 17
  },
  "José Miguel Castillo Calvín": {
    "X": 256
  },
  "José Miguel González Robles": {
    "XIV": 29
  },
  "José Miñones Conde": {
    "XV": 280
  },
  "José Máximo López Vilaboa": {
    "X": 385
  },
  "José Ortiz Galván": {
    "XIV": 134
  },
  "José Ramírez del Río": {
    "XIII": 304,
    "XIV": 93,
    "XV": 70
  },
  "José Ramón García Cañal": {
    "XI": 113,
    "XII": 281
  },
  "José Ramón García Hernández": {
    "X": 388,
    "XI": 310,
    "XII": 89
  },
  "José Ramón Gómez Besteiro": {
    "XV": 144
  },
  "José Ramón Ortega Domínguez": {
    "XIV": 368
  },
  "José Segura Clavell": {
    "X": 30
  },
  "José Simón Marín": {
    "XIII": 306
  },
  "José Vicente Marí Bosó": {
    "XI": 141,
    "XII": 140,
    "XV": 188
  },
  "José Zaragoza Alonso": {
    "X": 253,
    "XI": 218,
    "XII": 263,
    "XIII": 66,
    "XIV": 196,
    "XV": 35
  },
  "José Ángel Alonso Pérez": {
    "XIV": 244
  },
  "Juan Andrés Bayón Rolo": {
    "XV": 382
  },
  "Juan Antonio Abad Pérez": {
    "X": 87
  },
  "Juan Antonio Callejas Cano": {
    "XIV": 35
  },
  "Juan Antonio Delgado Ramos": {
    "XI": 82,
    "XII": 142,
    "XIII": 134,
    "XIV": 387
  },
  "Juan Antonio González Gracia": {
    "XV": 228
  },
  "Juan Antonio Lorenzo Cazorla": {
    "XV": 354
  },
  "Juan Antonio López de Uralde Garmendia": {
    "XI": 48,
    "XII": 196,
    "XIII": 121,
    "XIV": 205
  },
  "Juan Antonio Rojas Manrique": {
    "XV": 156
  },
  "Juan Antonio Valero Morales": {
    "XV": 78
  },
  "Juan Bernardo Fuentes Curbelo": {
    "XIV": 359
  },
  "Juan Bertomeu Bertomeu": {
    "X": 278
  },
  "Juan Bravo Baena": {
    "XI": 46,
    "XII": 141,
    "XV": 9
  },
  "Juan Carlos Aparicio Pérez": {
    "X": 13
  },
  "Juan Carlos Campo Moreno": {
    "XI": 126,
    "XII": 31,
    "XIII": 204,
    "XIV": 44
  },
  "Juan Carlos Corcuera Plaza": {
    "X": 208
  },
  "Juan Carlos Girauta Vidal": {
    "XI": 228,
    "XII": 339,
    "XIII": 223
  },
  "Juan Carlos Grau Reinés": {
    "X": 5
  },
  "Juan Carlos Jerez Antequera": {
    "XV": 18
  },
  "Juan Carlos Lagares Flores": {
    "X": 58
  },
  "Juan Carlos Ruiz Boix": {
    "XV": 68
  },
  "Juan Carlos Segura Just": {
    "XIV": 380
  },
  "Juan Carlos Vera Pró": {
    "X": 119,
    "XI": 151,
    "XII": 207
  },
  "Juan Cuatrecasas Asua": {
    "XIII": 313,
    "XIV": 303
  },
  "Juan Diego Requena Ruiz": {
    "XIV": 79,
    "XV": 131
  },
  "Juan Francisco Serrano Martínez": {
    "XIII": 21,
    "XIV": 158,
    "XV": 40
  },
  "Juan Ignacio López-Bas Valero": {
    "XIII": 183,
    "XIV": 383
  },
  "Juan Ignacio Zoido Álvarez": {
    "XI": 58,
    "XII": 215
  },
  "Juan Jiménez Tortosa": {
    "XI": 318,
    "XII": 330
  },
  "Juan José Aizcorbe Torra": {
    "XIV": 151,
    "XV": 52
  },
  "Juan José Cortés Fernández": {
    "XIII": 101
  },
  "Juan José Matarí Sáez": {
    "X": 95,
    "XI": 59,
    "XII": 44,
    "XIII": 40,
    "XIV": 48
  },
  "Juan Luis Gordo Pérez": {
    "X": 65,
    "XI": 22,
    "XII": 157
  },
  "Juan Luis Pedreño Molina": {
    "XIV": 132,
    "XV": 339
  },
  "Juan Luis Soto Burillo": {
    "XIII": 105,
    "XIV": 275
  },
  "Juan Luis Steegmann Olmedillas": {
    "XIV": 135
  },
  "Juan Manuel Albendea Pabón": {
    "X": 12
  },
  "Juan Manuel Constenla Carbón": {
    "XIV": 378
  },
  "Juan Manuel Del Olmo Ibáñez": {
    "XI": 72,
    "XII": 38
  },
  "Juan Manuel Juncal Rodríguez": {
    "XI": 111,
    "XII": 124
  },
  "Juan Manuel Moreno Bonilla": {
    "X": 221
  },
  "Juan María Vázquez Rojas": {
    "XI": 30,
    "XII": 79
  },
  "Juan Moscoso del Prado Hernández": {
    "X": 207
  },
  "Juan Pedro Yllanes Suárez": {
    "XI": 87,
    "XII": 93
  },
  "Juan Vicente Pérez Aras": {
    "X": 407,
    "XI": 167,
    "XII": 62
  },
  "Juan de Dios Ruano Gómez": {
    "X": 98
  },
  "Juana Amalia Rodríguez Hernández": {
    "XI": 317,
    "XII": 306
  },
  "Julia Parra Aparicio": {
    "XV": 210
  },
  "Julia de Micheo Carrillo-Albornoz": {
    "X": 369
  },
  "Julio Del Valle de Iscar": {
    "XIV": 360
  },
  "Julio Lleonart Crespo": {
    "X": 412
  },
  "Julio Navalpotro Gómez": {
    "XIV": 366
  },
  "Julio Utrilla Cano": {
    "XIV": 328
  },
  "Julio Villarrubia Mediavilla": {
    "X": 133
  },
  "Julián López Milla": {
    "XI": 206,
    "XII": 30
  },
  "Justo Fernández González": {
    "XIII": 116
  },
  "Júlia Boada Danés": {
    "XV": 332
  },
  "Kissy Chandiramani Ramesh": {
    "XII": 390
  },
  "Laia Cañigueral Olivé": {
    "XIII": 259
  },
  "Laia Ortiz Castellví": {
    "X": 345
  },
  "Lander Martínez Hierro": {
    "XV": 87
  },
  "Laura Berja Vega": {
    "XIII": 22,
    "XIV": 70
  },
  "Laura Borràs Castanyer": {
    "XIII": 311,
    "XIV": 25
  },
  "Laura Carmen Seara Sobrado": {
    "X": 269
  },
  "Laura López Domínguez": {
    "XIV": 263
  },
  "Laura María Lima García": {
    "XV": 155
  },
  "Laura Vergara Román": {
    "XV": 408
  },
  "Leire Iglesias Santiago": {
    "X": 115
  },
  "Leire Pajín Iraola": {
    "X": 91
  },
  "Leopoldo Barreda de los Ríos": {
    "X": 149,
    "XI": 315,
    "XII": 47
  },
  "Lilith Verstrynge Revuelta": {
    "XV": 322
  },
  "Llanos De Luna Tobarra": {
    "XIV": 157,
    "XV": 174
  },
  "Loly De Juan de Miguel": {
    "X": 433
  },
  "Loreto Cascales Martínez": {
    "XI": 200,
    "XII": 130
  },
  "Lourdes Ciuró i Buldó": {
    "X": 197,
    "XI": 342,
    "XII": 212
  },
  "Lourdes Guillén Figuerola": {
    "XIII": 180
  },
  "Lourdes Muñoz Santamaría": {
    "X": 389
  },
  "Lourdes Méndez Monasterio": {
    "X": 258,
    "XIII": 111,
    "XIV": 177,
    "XV": 203
  },
  "Luc Andre Diouf Dioh": {
    "XIII": 231,
    "XIV": 221,
    "XV": 142
  },
  "Lucila María Corral Ruiz": {
    "X": 408
  },
  "Lucía Martín González": {
    "XI": 131,
    "XII": 270
  },
  "Lucía Muñoz Dalda": {
    "XIII": 321,
    "XIV": 335
  },
  "Luis Alberto Marín González": {
    "XV": 227
  },
  "Luis Alfonso Rey de las Heras": {
    "XV": 11
  },
  "Luis Antonio Gómez Piña": {
    "XV": 396
  },
  "Luis Carlos Sahuquillo García": {
    "X": 125,
    "XI": 8,
    "XII": 1,
    "XIII": 3,
    "XIV": 2,
    "XV": 10
  },
  "Luis Clemente Guadilla": {
    "XIII": 122
  },
  "Luis Gestoso de Miguel": {
    "XIV": 131
  },
  "Luis López Jiménez": {
    "X": 100
  },
  "Luis María Beamonte Mesa": {
    "XV": 297
  },
  "Luis Miguel Salvador García": {
    "XI": 66,
    "XII": 16
  },
  "Luis Planas Puchades": {
    "XIII": 148,
    "XIV": 148,
    "XV": 56
  },
  "Luis Santamaría Ruiz": {
    "XIII": 219,
    "XIV": 269
  },
  "Luis Tudanca Fernández": {
    "X": 343
  },
  "Luisa Sanz Martínez": {
    "XV": 91
  },
  "Lázaro Azorín Salar": {
    "XIV": 371,
    "XV": 273
  },
  "Lídia Guinart Moreno": {
    "XI": 182,
    "XII": 264,
    "XIII": 82,
    "XIV": 202,
    "XV": 272
  },
  "Macarena Lorente Anaya": {
    "XV": 48
  },
  "Macarena Montesinos de Miguel": {
    "X": 350,
    "XIII": 287,
    "XIV": 346,
    "XV": 216
  },
  "Macarena Olona Choclán": {
    "XIII": 56,
    "XIV": 84
  },
  "Magdalena Margarita Contestí Rosselló": {
    "XIII": 316
  },
  "Magdalena Valerio Cordero": {
    "X": 124,
    "XIII": 269,
    "XIV": 140
  },
  "Maite Ariztegui Larrañaga": {
    "X": 340
  },
  "Manuel Arribas Maroto": {
    "XIV": 369,
    "XV": 96
  },
  "Manuel Blasco Marqués": {
    "XI": 275,
    "XII": 19
  },
  "Manuel Cervera Taulet": {
    "X": 314
  },
  "Manuel Chaves González": {
    "X": 252
  },
  "Manuel Cobo Vega": {
    "XV": 324
  },
  "Manuel Cruz Rodríguez": {
    "XII": 262
  },
  "Manuel Gabriel González Ramos": {
    "X": 11,
    "XI": 266,
    "XII": 239,
    "XIII": 47,
    "XIV": 147
  },
  "Manuel García Félix": {
    "XV": 25
  },
  "Manuel Hernández Muñoz": {
    "XIII": 174
  },
  "Manuel Ibáñez Gimeno": {
    "X": 384
  },
  "Manuel Lago Peñas": {
    "XV": 375
  },
  "Manuel Luis Torres Herrera": {
    "X": 170,
    "XII": 383
  },
  "Manuel Mariscal Zabala": {
    "XIII": 266,
    "XIV": 153,
    "XV": 263
  },
  "Manuel Mestre Barea": {
    "XIII": 305,
    "XIV": 268
  },
  "Manuel Monereo Pérez": {
    "XII": 182
  },
  "Manuel Mora Bernat": {
    "X": 232
  },
  "Manuel Pezzi Cereto": {
    "X": 78
  },
  "Manuel Torres Fernández": {
    "XII": 392
  },
  "Manuel de la Rocha Rubí": {
    "X": 395
  },
  "Mar Cotelo Balmaseda": {
    "XII": 73
  },
  "Maravillas Concepción Falcón Dacal": {
    "X": 46
  },
  "Marc Lamuà Estañol": {
    "XI": 305,
    "XII": 260,
    "XIII": 78,
    "XIV": 200,
    "XV": 110
  },
  "Marc Solsona Aixalà": {
    "X": 190
  },
  "Marcelo Expósito Prieto": {
    "XI": 107,
    "XII": 101
  },
  "Marcial Gómez Balsera": {
    "XI": 69,
    "XII": 116,
    "XIII": 141
  },
  "Marcos De Quinto Romero": {
    "XIII": 124,
    "XIV": 325
  },
  "Margarita Martín Rodríguez": {
    "XV": 146
  },
  "Margarita Prohens Rigo": {
    "XIII": 19,
    "XIV": 243
  },
  "Margarita Pérez Herraiz": {
    "X": 393,
    "XI": 38,
    "XII": 3
  },
  "Margarita Robles Fernández": {
    "XII": 65,
    "XIII": 69,
    "XIV": 42,
    "XV": 233
  },
  "Margarita Varela Lema": {
    "X": 403
  },
  "Margarita del Carmen del Cid Muñoz": {
    "X": 236
  },
  "Maria Carme Sayós i Motilla": {
    "X": 386
  },
  "Maria Josep Picó Garcés": {
    "XIV": 408
  },
  "Marian Beitialarrangoitia Lizarralde": {
    "XI": 335,
    "XII": 341
  },
  "Mariana de Gracia Canales Duque": {
    "XIII": 2,
    "XIV": 3
  },
  "Mariano Pérez-Hickman Silván": {
    "X": 390,
    "XII": 386
  },
  "Mariano Rajoy Brey": {
    "X": 178,
    "XI": 295,
    "XII": 105
  },
  "Mariano Sánchez Escobar": {
    "XIII": 150,
    "XIV": 227
  },
  "Maribel García López": {
    "XIII": 102,
    "XIV": 39,
    "XV": 49
  },
  "Maribel Sánchez Torregrosa": {
    "XV": 177
  },
  "Maribel Vaquero Montero": {
    "XV": 303
  },
  "Marije Fullaondo la Cruz": {
    "XV": 291
  },
  "Marina Ortega Otero": {
    "XIII": 63,
    "XIV": 34
  },
  "Mario Bedera Bravo": {
    "X": 206
  },
  "Mario Cortés Carballo": {
    "XIV": 317,
    "XV": 85
  },
  "Mario Francisco José Flores Lanuza": {
    "X": 321
  },
  "Mario Garcés Sanagustín": {
    "XIII": 128,
    "XIV": 219
  },
  "Mario Mingo Zapatero": {
    "X": 156
  },
  "Mariona Illamola Dausà": {
    "XIV": 22
  },
  "Marisa Saavedra Muñoz": {
    "XIII": 339,
    "XIV": 348
  },
  "Marisol Sánchez Jódar": {
    "XIII": 110,
    "XIV": 276
  },
  "Marta Domínguez Álvarez": {
    "XI": 77
  },
  "Marta González Vázquez": {
    "X": 264,
    "XI": 115,
    "XII": 86,
    "XIII": 44,
    "XIV": 237,
    "XV": 200
  },
  "Marta Gracia Blanco": {
    "XV": 370
  },
  "Marta Lois González": {
    "XV": 267
  },
  "Marta Madrenas i Mir": {
    "XV": 245
  },
  "Marta Martín Llaguno": {
    "XI": 232,
    "XII": 8,
    "XIII": 149,
    "XIV": 155
  },
  "Marta María Rivera de la Cruz": {
    "XI": 231,
    "XII": 98,
    "XIII": 125,
    "XV": 285
  },
  "Marta Rosique i Saltor": {
    "XIII": 261,
    "XIV": 185
  },
  "Marta Sibina Camps": {
    "XI": 132,
    "XII": 269
  },
  "Marta Sorlí Fresquet": {
    "XI": 282,
    "XII": 222
  },
  "Marta Torrado de Castro": {
    "X": 286
  },
  "Marta Trenzano Rubio": {
    "XV": 220
  },
  "Marta Varela Pazos": {
    "XV": 347
  },
  "Martina Velarde Gómez": {
    "XIII": 245,
    "XIV": 235,
    "XV": 169
  },
  "Martí Barberà i Montserrat": {
    "X": 193
  },
  "María Adrio Taracido": {
    "XV": 139
  },
  "María Amparo Ferrando Sendra": {
    "X": 349
  },
  "María Amparo Moya Sanz": {
    "XIII": 117
  },
  "María Angelina Costa Palacios": {
    "X": 144
  },
  "María Araceli Poblador Pacheco": {
    "XV": 39
  },
  "María Arenales Serrano Argüello": {
    "X": 327
  },
  "María Aránzazu Miguélez Pariente": {
    "X": 210
  },
  "María Ascensión Carreño Fernández": {
    "X": 249,
    "XI": 110,
    "XII": 137
  },
  "María Ascensión Figueres Górriz": {
    "X": 10
  },
  "María Asunción Jacoba Pía De la Concha García-Mauriño": {
    "XI": 89,
    "XII": 325
  },
  "María Aurora Flórez Rodríguez": {
    "XI": 152,
    "XII": 288
  },
  "María Auxiliadora Honorato Chulián": {
    "XI": 84,
    "XII": 172
  },
  "María Auxiliadora Pérez Díaz": {
    "XIV": 160
  },
  "María Beatriz Corredor Sierra": {
    "XIII": 267,
    "XIV": 286
  },
  "María Belén Guerra Mansito": {
    "XI": 214
  },
  "María Belén Juste Picón": {
    "X": 316
  },
  "María Blanca Puyuelo del Val": {
    "X": 231
  },
  "María Caridad García Álvarez": {
    "X": 68
  },
  "María Carmen Castellano i Fernández": {
    "X": 435
  },
  "María Carmen Castilla Álvarez": {
    "XV": 15
  },
  "María Carmen Iglesias Camarero": {
    "XII": 391
  },
  "María Carmen Martínez Granados": {
    "XIII": 319,
    "XIV": 60
  },
  "María Carmen Rodríguez Flores": {
    "X": 374
  },
  "María Carmen Sánchez Díaz": {
    "X": 112,
    "XV": 72
  },
  "María Carmen Álvarez-Arenas Cisneros": {
    "X": 74,
    "XI": 222,
    "XII": 37
  },
  "María Carvalho Dantas": {
    "XIII": 262,
    "XIV": 190
  },
  "María Concepció Tarruella Tomás": {
    "X": 191
  },
  "María Concepción Gutiérrez del Castillo": {
    "X": 121
  },
  "María Concepción Ruiz López": {
    "XIII": 130
  },
  "María Consuelo Rumí Ibáñez": {
    "X": 164
  },
  "María Cristina Suárez-Bárcena Blasco": {
    "X": 368
  },
  "María Cuesta Rodríguez": {
    "XV": 44
  },
  "María Dolores Alba Mullor": {
    "XII": 84
  },
  "María Dolores Arteaga Espinosa de los Monteros": {
    "XIII": 169
  },
  "María Dolores Bolarín Sánchez": {
    "X": 309,
    "XII": 371
  },
  "María Dolores Corujo Berriel": {
    "XV": 187
  },
  "María Dolores De Cospedal García": {
    "XI": 226,
    "XII": 292
  },
  "María Dolores Galovart Carrera": {
    "XI": 242,
    "XII": 326
  },
  "María Dolores Marcos Moyano": {
    "XI": 40,
    "XII": 46,
    "XIV": 402
  },
  "María Dolores Narváez Bandera": {
    "XIII": 50,
    "XIV": 154
  },
  "María Elena Álvarez Simón": {
    "XI": 343
  },
  "María Elisa Vedrina Conesa": {
    "XV": 383
  },
  "María Elvira Rodríguez Herrer": {
    "X": 41,
    "XIV": 123,
    "XV": 404
  },
  "María Eugenia Carballedo Berlanga": {
    "XV": 341
  },
  "María Eugenia Romero Rodríguez": {
    "X": 61,
    "XI": 99,
    "XII": 76
  },
  "María Felicidad Rodríguez Sánchez": {
    "X": 54
  },
  "María Fernández Pérez": {
    "XIV": 393
  },
  "María Freixanet Mateo": {
    "XIII": 201
  },
  "María Fátima Báñez García": {
    "X": 26,
    "XI": 62,
    "XII": 317
  },
  "María Gloria Elizo Serrano": {
    "XI": 41,
    "XII": 147,
    "XIII": 72,
    "XIV": 300
  },
  "María González Veracruz": {
    "X": 104,
    "XI": 329,
    "XII": 166
  },
  "María Guadalupe González Taño": {
    "XIII": 28
  },
  "María Guadalupe Martín González": {
    "X": 126,
    "XI": 202,
    "XII": 29
  },
  "María Guijarro Ceballos": {
    "XIII": 153,
    "XIV": 136,
    "XV": 114
  },
  "María Inmaculada Oria López": {
    "XIV": 370
  },
  "María Isabel Blanco Llamas": {
    "XIII": 317
  },
  "María Isabel Medina Suárez": {
    "XI": 81
  },
  "María Isabel Pozuelo Meño": {
    "X": 128
  },
  "María Isabel Prieto Serrano": {
    "XV": 71
  },
  "María Isabel Salud Areste": {
    "XII": 243
  },
  "María Jesús Bonilla Domínguez": {
    "X": 120,
    "XI": 34,
    "XII": 108,
    "XIII": 351
  },
  "María Jesús Calva Ruiz": {
    "XIII": 123
  },
  "María Jesús Montero Cuadrado": {
    "XIII": 320,
    "XIV": 225,
    "XV": 337
  },
  "María Jesús Moro Almaraz": {
    "X": 34,
    "XI": 11,
    "XII": 12,
    "XIII": 34,
    "XIV": 91,
    "XV": 151
  },
  "María Jesús Serrano Jiménez": {
    "XI": 137,
    "XII": 193
  },
  "María Jesús Susinos Tarrero": {
    "X": 223
  },
  "María José Calderón Díaz": {
    "XIII": 190
  },
  "María José García-Pelayo Jurado": {
    "XI": 32,
    "XII": 165,
    "XIII": 100,
    "XIV": 17
  },
  "María José Rodríguez Ramírez": {
    "X": 130
  },
  "María José Rodríguez de Millán Parro": {
    "XV": 344
  },
  "María José Vázquez Morillo": {
    "X": 113
  },
  "María Lourdes Ramírez Martín": {
    "XV": 60
  },
  "María Luisa Alonso García": {
    "XIII": 178
  },
  "María Luisa Carcedo Roces": {
    "X": 266,
    "XIII": 240,
    "XIV": 270
  },
  "María Luisa Del Moral Leal": {
    "XIII": 70,
    "XV": 3
  },
  "María Luisa Faneca López": {
    "XIII": 55,
    "XIV": 253,
    "XV": 167
  },
  "María Luisa García Gurrutxaga": {
    "XIV": 400,
    "XV": 113
  },
  "María Luisa González Santín": {
    "X": 382
  },
  "María Luisa Sánchez Trancoso": {
    "X": 437
  },
  "María Luisa Vilches Ruiz": {
    "XIII": 228,
    "XIV": 332
  },
  "María Luz Bajo Prieto": {
    "X": 250,
    "XI": 217,
    "XII": 134
  },
  "María Luz Martínez Seijo": {
    "XI": 109,
    "XII": 297,
    "XIII": 96,
    "XIV": 251,
    "XV": 63
  },
  "María Luz Rodríguez Fernández": {
    "XI": 105
  },
  "María Magdalena Nevado del Campo": {
    "XIV": 293
  },
  "María Marrodán Funes": {
    "XIII": 312,
    "XIV": 302
  },
  "María Martín Revuelta": {
    "X": 406
  },
  "María Mercedes Fernández González": {
    "X": 332,
    "XV": 82
  },
  "María Mercedes Pérez Merino": {
    "XIV": 382
  },
  "María Mercè Perea i Conillas": {
    "XI": 269,
    "XII": 252,
    "XIII": 67,
    "XIV": 203,
    "XV": 19
  },
  "María Montserrat García Chavarría": {
    "XIII": 92,
    "XIV": 304,
    "XV": 380
  },
  "María Muñoz Vidal": {
    "XIII": 191,
    "XIV": 333
  },
  "María Márquez Guerrero": {
    "XIII": 217,
    "XIV": 236
  },
  "María Olga Alonso Suárez": {
    "XIII": 103,
    "XIV": 72
  },
  "María Olga Iglesias Fontal": {
    "X": 261
  },
  "María Paloma Rodríguez Vázquez": {
    "X": 376
  },
  "María Paz Lago Martínez": {
    "X": 139
  },
  "María Piedra Escrita Jiménez Díaz": {
    "X": 353
  },
  "María Pilar Alegría Continente": {
    "X": 242,
    "XV": 274
  },
  "María Pilar Alía Aguado": {
    "XV": 183
  },
  "María Pilar Ardanza Uribarren": {
    "XI": 117
  },
  "María Pilar Lucio Carrasco": {
    "X": 111,
    "XI": 326,
    "XII": 178
  },
  "María Pilar Ramallo Vázquez": {
    "XIV": 117
  },
  "María Rosa Martínez Rodríguez": {
    "XI": 56,
    "XII": 186
  },
  "María Sainz Martín": {
    "XV": 384
  },
  "María Sandra Julià Julià": {
    "XII": 354,
    "XIII": 194
  },
  "María Sandra Moneo Díez": {
    "X": 311,
    "XI": 291,
    "XII": 314,
    "XIII": 286,
    "XIV": 337,
    "XV": 204
  },
  "María Soledad Cruz-Guzmán García": {
    "XIII": 215,
    "XIV": 159,
    "XV": 319
  },
  "María Soledad Pérez Domínguez": {
    "X": 110,
    "XI": 170,
    "XII": 177
  },
  "María Soraya Rodríguez Ramos": {
    "X": 257,
    "XI": 316,
    "XII": 153
  },
  "María Soraya Sáenz de Santamaría Antón": {
    "X": 230,
    "XI": 259,
    "XII": 285
  },
  "María Such Palomares": {
    "XI": 161,
    "XII": 238
  },
  "María Tamara Raya Rodríguez": {
    "XI": 332,
    "XII": 322,
    "XIII": 342,
    "XIV": 112
  },
  "María Teresa Angulo Romero": {
    "X": 148,
    "XI": 299,
    "XII": 296,
    "XIV": 113
  },
  "María Teresa Arévalo Caraballo": {
    "XII": 299
  },
  "María Teresa Cobaleda Hernández": {
    "X": 362
  },
  "María Teresa Jiménez-Becerril Barrio": {
    "XIII": 283,
    "XIV": 179
  },
  "María Teresa López Álvarez": {
    "XIV": 327
  },
  "María Teresa Martín Pozo": {
    "X": 354
  },
  "María Teresa Pérez Díaz": {
    "XIII": 229
  },
  "María Teresa Rodríguez Barahona": {
    "X": 396
  },
  "María Teresa de Lara Carbó": {
    "X": 80,
    "XI": 221,
    "XII": 36
  },
  "María Torres Tejada": {
    "XII": 366,
    "XV": 368
  },
  "María Valentina Martínez Ferro": {
    "X": 402,
    "XII": 380,
    "XIII": 114,
    "XIV": 341
  },
  "María Victoria Domínguez Paredes": {
    "XIII": 177
  },
  "María Victoria Rosell Aguilar": {
    "XI": 95,
    "XIII": 15,
    "XIV": 41
  },
  "María Vilas Liñares": {
    "XIII": 355
  },
  "María Virginia Millán Salmerón": {
    "XI": 220,
    "XII": 139,
    "XIII": 226
  },
  "María Virtudes Cediel Martínez": {
    "X": 401
  },
  "María Virtudes Monteserín Rodríguez": {
    "X": 322
  },
  "María Yolanda Casaus Rodríguez": {
    "X": 423
  },
  "María de la Cabeza Ruiz Solás": {
    "XIII": 265,
    "XIV": 301,
    "XV": 283
  },
  "María de la Concepción de Santa Ana Fernández": {
    "X": 214,
    "XI": 52,
    "XII": 90
  },
  "María de la O Ares Martínez-Fortún": {
    "X": 4
  },
  "María de la O Redondo Calvillo": {
    "XIV": 106
  },
  "María de la Paz Del Moral Milla": {
    "XI": 13
  },
  "María de las Mercedes Cantalapiedra Álvarez": {
    "XV": 234
  },
  "María de las Mercedes Gámez García": {
    "X": 425
  },
  "María de las Nieves Ramírez Moreno": {
    "XV": 5
  },
  "María de los Reyes Romero Vilches": {
    "XIII": 303,
    "XIV": 174,
    "XV": 307
  },
  "María de los Ángeles Fernández-Ahuja García": {
    "X": 367
  },
  "María del Carmen Dueñas Martínez": {
    "XI": 211,
    "XII": 227
  },
  "María del Carmen Duque Palacios": {
    "X": 430
  },
  "María del Carmen Fortea Millán": {
    "X": 405
  },
  "María del Carmen González Guinda": {
    "XI": 27,
    "XII": 111,
    "XIII": 88,
    "XIV": 288
  },
  "María del Carmen Hernández Bento": {
    "XII": 53,
    "XIII": 292
  },
  "María del Carmen Navarro Cruz": {
    "X": 47,
    "XII": 360
  },
  "María del Carmen Pita Cárdenes": {
    "XI": 73,
    "XII": 150,
    "XIII": 4,
    "XIV": 356
  },
  "María del Carmen Quintanilla Barba": {
    "X": 300,
    "XI": 157,
    "XII": 43
  },
  "María del Carmen Rodríguez Maniega": {
    "X": 348
  },
  "María del Carmen Silva Rego": {
    "X": 51
  },
  "María del Mar Arnaiz García": {
    "X": 410
  },
  "María del Mar Baena Azuaga": {
    "X": 371
  },
  "María del Mar García Puig": {
    "XI": 125,
    "XII": 265,
    "XIII": 341,
    "XIV": 265
  },
  "María del Mar González Bella": {
    "XV": 251
  },
  "María del Mar Rominguera Salazar": {
    "X": 399,
    "XI": 293,
    "XII": 183,
    "XIII": 277
  },
  "María del Mar Sánchez Sierra": {
    "XV": 281
  },
  "María del Mar Vázquez Jiménez": {
    "XV": 76
  },
  "María del Pilar Rodríguez Gómez": {
    "XIV": 273
  },
  "María del Puerto Gallego Arriola": {
    "X": 127,
    "XI": 112,
    "XII": 128
  },
  "María del Rocío De Frutos Madrazo": {
    "XI": 148,
    "XII": 277
  },
  "María del Socorro Cuesta Rodríguez": {
    "XV": 44
  },
  "María Ángeles Adán de la Paz": {
    "XIII": 181
  },
  "María Ángeles Esteller Ruedas": {
    "X": 297,
    "XII": 373
  },
  "María Ángeles Marra Domínguez": {
    "XIII": 104,
    "XIV": 46
  },
  "María Ángeles Rosado Peinado": {
    "XIII": 308
  },
  "Mateo Isern Estela": {
    "XI": 333
  },
  "Mateo Luna Alcaide": {
    "X": 436
  },
  "Matilde Pastora Asian González": {
    "X": 172,
    "XI": 205,
    "XII": 57
  },
  "Melisa Rodríguez Hernández": {
    "XI": 229,
    "XII": 340,
    "XIII": 118
  },
  "Mercedes González Fernández": {
    "XV": 279
  },
  "Mercedes Jara Moreno": {
    "XIV": 377
  },
  "Mercedes Otero García": {
    "XV": 386
  },
  "Mercedes Pérez Merino": {
    "XIII": 73
  },
  "Meritxell Batet Lamaña": {
    "X": 330,
    "XI": 174,
    "XII": 251,
    "XIII": 86,
    "XIV": 215,
    "XV": 326
  },
  "Mertxe Aizpurua Arzallus": {
    "XIII": 210,
    "XIV": 69,
    "XV": 300
  },
  "Micaela Navarro Garzón": {
    "XI": 116,
    "XII": 125
  },
  "Miguel Anxo Fernández Bello": {
    "XI": 271,
    "XII": 343
  },
  "Miguel Arias Cañete": {
    "X": 35
  },
  "Miguel Barrachina Ros": {
    "XI": 42,
    "XII": 205
  },
  "Miguel Lorenzo Torres": {
    "XI": 240,
    "XII": 295
  },
  "Miguel Sánchez de Alcázar Ocaña": {
    "X": 40
  },
  "Miguel Tellado Filgueira": {
    "XV": 26
  },
  "Miguel Vila Gómez": {
    "XI": 346,
    "XII": 226
  },
  "Miguel Ángel Bustamante Martín": {
    "XII": 242,
    "XIV": 385
  },
  "Miguel Ángel Castellón Rubio": {
    "XIV": 74
  },
  "Miguel Ángel Cortizo Nieto": {
    "X": 157
  },
  "Miguel Ángel Cortés Martín": {
    "X": 177
  },
  "Miguel Ángel Garaulet Rodríguez": {
    "XI": 237,
    "XII": 114,
    "XIII": 145
  },
  "Miguel Ángel González Caballero": {
    "XIII": 108,
    "XIV": 222
  },
  "Miguel Ángel Gutiérrez Vivas": {
    "XI": 164,
    "XII": 96,
    "XIII": 62,
    "XIV": 375
  },
  "Miguel Ángel Heredia Díaz": {
    "X": 37,
    "XI": 6,
    "XII": 50
  },
  "Miguel Ángel Jerez Juan": {
    "XIV": 124
  },
  "Miguel Ángel Paniagua Núñez": {
    "XI": 209,
    "XII": 122,
    "XIV": 240,
    "XV": 323
  },
  "Miguel Ángel Quintanilla Navarro": {
    "XIV": 399,
    "XV": 181
  },
  "Miguel Ángel Sastre Uyá": {
    "XV": 206
  },
  "Miguel Ángel Viso Diéguez": {
    "XI": 178,
    "XII": 103
  },
  "Mikel Legarda Uriarte": {
    "XI": 120,
    "XII": 232,
    "XIII": 238,
    "XIV": 95,
    "XV": 306
  },
  "Mikel Otero Gabirondo": {
    "XV": 398
  },
  "Milagros Marcos Ortega": {
    "XIII": 94,
    "XIV": 92,
    "XV": 320
  },
  "Milagros Tolón Jaime": {
    "XV": 158
  },
  "Milena Herrera García": {
    "XV": 186
  },
  "Miquel Iceta i Llorens": {
    "XV": 147
  },
  "Miquel Ramis Socias": {
    "X": 3
  },
  "Mireia Borrás Pabón": {
    "XIV": 142
  },
  "Mireia Vehí Cantenys": {
    "XIV": 86
  },
  "Miren Gorrotxategi Azurmendi": {
    "XIII": 132
  },
  "Miriam Alconchel Gonzaga": {
    "XI": 127,
    "XII": 276
  },
  "Miriam Guadalupe Blasco Soto": {
    "X": 49
  },
  "Mirian Guardiola Salmerón": {
    "XV": 351
  },
  "Modesto Pose Mesura": {
    "XV": 129
  },
  "Mohammed Chaib Akhdim": {
    "XII": 379
  },
  "Montse Mínguez García": {
    "XIII": 93,
    "XIV": 199,
    "XV": 80
  },
  "Montserrat Bassa Coll": {
    "XIII": 258,
    "XIV": 192,
    "XV": 313
  },
  "Montserrat Surroca i Comas": {
    "X": 200
  },
  "Mª Concepción Bravo Ibáñez": {
    "X": 86,
    "XI": 45
  },
  "Mª Isabel Moreno Fernández": {
    "XV": 361
  },
  "Mª Mar Blanco Garrido": {
    "XII": 127,
    "XIII": 326
  },
  "Mª Mercè Pigem i Palmés": {
    "X": 218
  },
  "Mª Olaia Fernández Davila": {
    "X": 291
  },
  "Míriam Nogueras i Camero": {
    "XI": 312,
    "XII": 217,
    "XIII": 310,
    "XIV": 27,
    "XV": 241
  },
  "Mónica Lafuente de la Torre": {
    "XI": 216
  },
  "Mónica Raquel Pérez Serna": {
    "X": 432
  },
  "Nacho Martín Blanco": {
    "XV": 173
  },
  "Nahuel González López": {
    "XV": 166
  },
  "Natalia González Peláez": {
    "XII": 368
  },
  "Natividad González Laso": {
    "XIV": 386
  },
  "Nayua Miriam Alba Goveli": {
    "XI": 146,
    "XII": 187
  },
  "Nerea Renteria Lasanta": {
    "XV": 399
  },
  "Noelia Cobo Pérez": {
    "XV": 321
  },
  "Noelia Núñez González": {
    "XV": 343
  },
  "Noelia Vera Ruiz-Herrera": {
    "XI": 192
  },
  "Noelia Vera Ruíz-Herrera": {
    "XII": 54,
    "XIII": 244,
    "XIV": 345
  },
  "Noemí Santana Perera": {
    "XV": 33
  },
  "Noemí Villagrasa Quero": {
    "XIII": 241,
    "XIV": 49
  },
  "Norma Pujol i Farré": {
    "XIII": 254,
    "XIV": 191
  },
  "Néstor Rego Candamil": {
    "XIV": 40,
    "XV": 238
  },
  "Obdulia Taboadela Álvarez": {
    "XV": 257
  },
  "Odón Elorza González": {
    "X": 334,
    "XI": 296,
    "XII": 204,
    "XIII": 216,
    "XIV": 324
  },
  "Ofelia Reyes Miranda": {
    "X": 419
  },
  "Olvido De la Rosa Baena": {
    "XV": 376
  },
  "Omar Anguita Pérez": {
    "XIV": 354
  },
  "Onintza Enbeita Maguregi": {
    "X": 370,
    "XI": 336
  },
  "Onofre Miralles Martín": {
    "XIV": 394
  },
  "Onésimo Eduardo González Martínez": {
    "XI": 252
  },
  "Oriol Almirón Ruiz": {
    "XV": 387
  },
  "Oriol Junqueras Vies": {
    "XIII": 333
  },
  "Orlena María Miguel Muñoz": {
    "XI": 255
  },
  "Oskar Matute García de Jalón": {
    "XII": 342,
    "XIII": 208,
    "XIV": 63,
    "XV": 287
  },
  "Ovidio Sánchez Díaz": {
    "X": 320
  },
  "Pablo Antuñano Colina": {
    "XV": 403
  },
  "Pablo Arangüena Fernández": {
    "XIII": 143,
    "XIV": 54
  },
  "Pablo Bellido Acevedo": {
    "XII": 176
  },
  "Pablo Bustinduy Amador": {
    "XI": 263,
    "XII": 310
  },
  "Pablo Cambronero Piqueras": {
    "XIII": 309,
    "XIV": 58
  },
  "Pablo Casado Blanco": {
    "X": 7,
    "XI": 308,
    "XII": 309,
    "XIII": 348,
    "XIV": 307
  },
  "Pablo Echenique Robba": {
    "XIII": 76,
    "XIV": 13
  },
  "Pablo García Pérez": {
    "X": 209
  },
  "Pablo Hispán Iglesias de Ussel": {
    "XIV": 309,
    "XV": 350
  },
  "Pablo Iglesias Turrión": {
    "XI": 153,
    "XII": 161,
    "XIII": 318,
    "XIV": 319
  },
  "Pablo Juan Calvo Liste": {
    "XIV": 213
  },
  "Pablo Martín Peré": {
    "X": 146
  },
  "Pablo Matos Mascareño": {
    "X": 169,
    "XI": 68,
    "XII": 51
  },
  "Pablo Montesinos Aguayo": {
    "XIII": 227,
    "XIV": 315
  },
  "Pablo Pérez Coronado": {
    "XV": 45
  },
  "Pablo Sáez Alonso-Muñumer": {
    "XIII": 251,
    "XIV": 278,
    "XV": 61
  },
  "Pablo Vázquez Vega": {
    "XV": 179
  },
  "Pablo Yáñez González": {
    "XI": 219
  },
  "Paloma García Gálvez": {
    "X": 357
  },
  "Paloma Gázquez Collado": {
    "XIII": 23,
    "XIV": 279
  },
  "Patricia Blanquer Alcaraz": {
    "X": 372,
    "XI": 197,
    "XII": 28,
    "XIII": 46,
    "XIV": 71,
    "XV": 170
  },
  "Patricia De las Heras Fernández": {
    "XIV": 248
  },
  "Patricia Hernández Gutiérrez": {
    "X": 131
  },
  "Patricia Otero Rodríguez": {
    "XV": 377
  },
  "Patricia Reyes Rivera": {
    "XI": 177,
    "XII": 34,
    "XIII": 87
  },
  "Patricia Rodríguez Calleja": {
    "XV": 51
  },
  "Patricia Rueda Perelló": {
    "XIII": 307,
    "XIV": 75,
    "XV": 293
  },
  "Patricia Sierra Rojas": {
    "XI": 168,
    "XII": 385
  },
  "Patxi López Álvarez": {
    "XI": 324,
    "XII": 123,
    "XIII": 197,
    "XIV": 61,
    "XV": 120
  },
  "Pau Marí Klose": {
    "XIII": 288,
    "XIV": 73
  },
  "Pau Morlà Florit": {
    "XIII": 5
  },
  "Paula Fernández Pena": {
    "XV": 379
  },
  "Pedro Acedo Penco": {
    "XII": 131
  },
  "Pedro Antonio Honrubia Hurtado": {
    "XIII": 247,
    "XIV": 68
  },
  "Pedro Arrojo Agudo": {
    "XI": 65,
    "XII": 55
  },
  "Pedro Casares Hontañón": {
    "XIV": 347,
    "XV": 336
  },
  "Pedro Duque Duque": {
    "XIII": 205,
    "XIV": 128
  },
  "Pedro Fernández Hernández": {
    "XIII": 300,
    "XIV": 146,
    "XV": 14
  },
  "Pedro Ignacio Gallardo Barrena": {
    "XV": 74
  },
  "Pedro Jesús Requejo Novoa": {
    "XIV": 85
  },
  "Pedro José Muñoz González": {
    "X": 1,
    "XI": 70,
    "XII": 155
  },
  "Pedro Luis Huguet Tous": {
    "XV": 36
  },
  "Pedro María Azpiazu Uriarte": {
    "X": 245,
    "XI": 121,
    "XII": 230
  },
  "Pedro Muñoz Abrines": {
    "XV": 236
  },
  "Pedro Navarro López": {
    "XIV": 220,
    "XV": 250
  },
  "Pedro Puy Fraga": {
    "XV": 199
  },
  "Pedro Quevedo Iturbe": {
    "X": 335,
    "XI": 348,
    "XII": 350,
    "XIV": 351
  },
  "Pedro Ramón Gómez de la Serna y Villacieros": {
    "X": 16,
    "XI": 7
  },
  "Pedro Samuel Martín García": {
    "XV": 150
  },
  "Pedro Saura García": {
    "X": 75,
    "XI": 179,
    "XII": 138,
    "XIII": 137,
    "XIV": 250
  },
  "Pedro Sánchez Pérez-Castejón": {
    "X": 381,
    "XI": 349,
    "XII": 347,
    "XIII": 324,
    "XIV": 274,
    "XV": 189
  },
  "Pepe Mercadal Baquero": {
    "XV": 190
  },
  "Percival Manglano Albacar": {
    "XIV": 390
  },
  "Pere Joan Pons Sampietro": {
    "XII": 304,
    "XIII": 6,
    "XIV": 223
  },
  "Pere Macias i Arau": {
    "X": 289
  },
  "Pilar Auxiliadora Serrano Boigas": {
    "XI": 5
  },
  "Pilar Barreiro Álvarez": {
    "X": 107
  },
  "Pilar Calvo Gómez": {
    "XIV": 381,
    "XV": 243
  },
  "Pilar Cancela Rodríguez": {
    "XI": 172,
    "XII": 271,
    "XIII": 90,
    "XIV": 292
  },
  "Pilar Cortés Bureta": {
    "X": 189,
    "XI": 215,
    "XII": 24
  },
  "Pilar Garrido Gutiérrez": {
    "XIII": 133,
    "XIV": 210
  },
  "Pilar Grande Pesquero": {
    "X": 136
  },
  "Pilar Marcos Domínguez": {
    "X": 377,
    "XII": 370,
    "XIV": 143
  },
  "Pilar Rojo Noguera": {
    "XI": 124,
    "XII": 129
  },
  "Pilar Vallugera Balañà": {
    "XIV": 88,
    "XV": 223
  },
  "Rafael Antonio Hernando Fraile": {
    "X": 36,
    "XI": 55,
    "XII": 85,
    "XV": 202
  },
  "Rafael Benigno Belmonte Gómez": {
    "XV": 175
  },
  "Rafael Calduch Cervera": {
    "X": 413
  },
  "Rafael Catalá Polo": {
    "XI": 21,
    "XII": 167,
    "XIII": 328
  },
  "Rafael Cofiño Fernández": {
    "XV": 122
  },
  "Rafael Fernández-Lomana Gutiérrez": {
    "XIV": 294
  },
  "Rafael José Vélez": {
    "XIV": 361
  },
  "Rafael Larreina Valderrama": {
    "X": 336
  },
  "Rafael Mayoral Perales": {
    "XI": 213,
    "XII": 257,
    "XIII": 163,
    "XIV": 336
  },
  "Rafael Merino López": {
    "X": 238,
    "XI": 134,
    "XII": 293
  },
  "Rafael Rodríguez-Ponga Salamanca": {
    "X": 317
  },
  "Rafael Simancas Simancas": {
    "X": 155,
    "XI": 171,
    "XII": 88,
    "XIII": 64,
    "XIV": 287,
    "XV": 229
  },
  "Rafaela Crespín Rubio": {
    "XIII": 275,
    "XIV": 107,
    "XV": 154
  },
  "Rafaela Romero Pozo": {
    "XV": 112
  },
  "Raimundo Viejo Viñas": {
    "XI": 94,
    "XII": 266
  },
  "Ramón Aguirre Rodríguez": {
    "X": 83,
    "XII": 320
  },
  "Ramón Antonio Socias Puig": {
    "XI": 193
  },
  "Ramón Jáuregui Atondo": {
    "X": 302
  },
  "Ramón Luis Molinary Malo": {
    "XI": 4
  },
  "Ramón Moreno Bustos": {
    "X": 159,
    "XI": 129,
    "XII": 214
  },
  "Raquel Alonso Hernández": {
    "XII": 361
  },
  "Raquel Clemente Muñoz": {
    "XV": 276
  },
  "Raquel Pedraja Sáinz": {
    "XIV": 362
  },
  "Raquel Sánchez Jiménez": {
    "XV": 83
  },
  "Raúl Cuevas Larrosa": {
    "XV": 395
  },
  "Raúl Díaz Marín": {
    "XV": 50
  },
  "Reyes Maroto Illera": {
    "XIII": 152,
    "XIV": 145
  },
  "Ricardo Antonio García Mira": {
    "XI": 150,
    "XII": 99
  },
  "Ricardo Chamorro Delmo": {
    "XIII": 297,
    "XIV": 125,
    "XV": 294
  },
  "Ricardo Cortés Lastra": {
    "XII": 353
  },
  "Ricardo Sixto Iglesias": {
    "X": 260,
    "XII": 206
  },
  "Ricardo Tarno Blanco": {
    "X": 303,
    "XI": 128,
    "XII": 213,
    "XIV": 388,
    "XV": 89
  },
  "Rita Gertrudis Bosaho Gori": {
    "XI": 285,
    "XII": 219
  },
  "Roberto García Morís": {
    "XIII": 314,
    "XIV": 231,
    "XV": 195
  },
  "Roberto Hernández Blázquez": {
    "XIII": 173
  },
  "Roberto Soravilla Fernández": {
    "X": 351
  },
  "Roberto Uriarte Torrealday": {
    "XIII": 329,
    "XIV": 207
  },
  "Rocío Aguirre Gil de Biedma": {
    "XV": 371
  },
  "Rocío De Meer Méndez": {
    "XIII": 295,
    "XIV": 340,
    "XV": 284
  },
  "Rocío López González": {
    "X": 154
  },
  "Rodrigo Gómez García": {
    "XI": 253,
    "XII": 143,
    "XIII": 249
  },
  "Rodrigo Jiménez Revuelta": {
    "XIV": 165
  },
  "Rogelio Araújo Gil": {
    "X": 355
  },
  "Román Ruiz Llamas": {
    "X": 241
  },
  "Rosa Aguilar Rivero": {
    "X": 145
  },
  "Rosa Ana Alonso Clusa": {
    "XI": 79,
    "XII": 279
  },
  "Rosa Delia Blanco Terán": {
    "X": 205
  },
  "Rosa María Cañizares Cabezas": {
    "X": 421
  },
  "Rosa María Díez González": {
    "X": 42
  },
  "Rosa María Medel Pérez": {
    "XIV": 355
  },
  "Rosa María Romero Sánchez": {
    "X": 313,
    "XI": 210,
    "XII": 56,
    "XIII": 188,
    "XIV": 36
  },
  "Rosa Quintana Carballo": {
    "XV": 197
  },
  "Rosana Pastor Muñoz": {
    "XI": 288,
    "XII": 221
  },
  "Rosana Pérez Fernández": {
    "X": 375
  },
  "Roser Maestro Moliner": {
    "XIII": 37,
    "XIV": 282
  },
  "Rubén Darío Vega Arias": {
    "XIV": 271
  },
  "Rubén Gómez González": {
    "XIII": 175
  },
  "Rubén Martínez Dalmau": {
    "XI": 350
  },
  "Rubén Moreno Palanques": {
    "X": 288,
    "XI": 145,
    "XII": 42
  },
  "Rubén Silvano Manso Olivar": {
    "XIV": 119
  },
  "Rufino Selva Guerrero": {
    "X": 417
  },
  "Sabino Cuadra Lasarte": {
    "X": 339
  },
  "Salvador Antonio De la Encina Ortega": {
    "X": 426,
    "XI": 136,
    "XII": 121
  },
  "Sandra Fernández Herranz": {
    "XV": 333
  },
  "Sandra Guaita Esteruelas": {
    "XIV": 208
  },
  "Sandra Pascual Rocamora": {
    "XV": 212
  },
  "Santi Rodríguez Serra": {
    "XV": 101
  },
  "Santiago Abascal Conde": {
    "XIII": 218,
    "XIV": 43,
    "XV": 317
  },
  "Santiago Cervera Soto": {
    "X": 152
  },
  "Santiago Lanzuela Marina": {
    "X": 64
  },
  "Santiago Martínez Rodríguez": {
    "X": 347
  },
  "Santiago Pérez López": {
    "XI": 24,
    "XII": 78
  },
  "Santos Cerdán León": {
    "XIII": 203,
    "XIV": 163,
    "XV": 57
  },
  "Sara Carreño Valero": {
    "XI": 143,
    "XII": 329
  },
  "Sara Cobos Trallero": {
    "X": 364
  },
  "Sara Giménez Giménez": {
    "XIII": 106,
    "XIV": 169
  },
  "Saúl Ramírez Freire": {
    "XI": 245,
    "XII": 145,
    "XIII": 139
  },
  "Sebastián Franquis Vera": {
    "X": 132,
    "XI": 289,
    "XII": 159
  },
  "Sebastián González Vázquez": {
    "X": 2
  },
  "Sebastián Jesús Ledesma Martín": {
    "XIV": 110
  },
  "Segundo González García": {
    "XI": 191,
    "XII": 327
  },
  "Sergi Miquel i Valentí": {
    "XII": 5,
    "XIII": 33,
    "XIV": 23
  },
  "Sergio Carlos Matos Castro": {
    "XV": 123
  },
  "Sergio Del Campo Estaún": {
    "XI": 236,
    "XII": 291,
    "XIII": 49
  },
  "Sergio Gutiérrez Prieto": {
    "XIII": 193,
    "XIV": 180,
    "XV": 232
  },
  "Sergio Pascual Peña": {
    "XI": 83,
    "XII": 173
  },
  "Sergio Sayas López": {
    "XIII": 146,
    "XIV": 55,
    "XV": 148
  },
  "Silverio Argüelles García": {
    "XV": 163
  },
  "Silvia Franco González": {
    "XV": 30
  },
  "Silvia Heredia Martín": {
    "X": 281,
    "XII": 136
  },
  "Silvia Oñate Moya": {
    "X": 409
  },
  "Silvia Valmaña Ochaíta": {
    "XI": 15,
    "XII": 26,
    "XIII": 192
  },
  "Sofía Acedo Reyes": {
    "XV": 69
  },
  "Sofía Fernández Castañón": {
    "XI": 76,
    "XII": 274,
    "XIII": 323,
    "XIV": 272
  },
  "Sofía Hernanz Costa": {
    "X": 141,
    "XI": 330,
    "XII": 305,
    "XIII": 242,
    "XIV": 289
  },
  "Sol Sánchez Maroto": {
    "XI": 184,
    "XII": 389
  },
  "Soledad Amada Velasco Baides": {
    "XII": 382
  },
  "Soledad Cabezón Ruiz": {
    "X": 137
  },
  "Sonia Ferrer Tesoro": {
    "XI": 331,
    "XII": 199,
    "XIII": 278,
    "XIV": 114
  },
  "Sonia Guerra López": {
    "XIII": 84,
    "XIV": 357,
    "XV": 20
  },
  "Sonsoles López Izquierdo": {
    "XIII": 91
  },
  "Soraya Mayo Alonso": {
    "XIII": 97
  },
  "Susana Camarero Benítez": {
    "X": 287
  },
  "Susana López Ares": {
    "XI": 43,
    "XII": 234
  },
  "Susana Ros Martínez": {
    "X": 101,
    "XIII": 213,
    "XIV": 53,
    "XV": 58
  },
  "Susana Sumelzo Jordán": {
    "X": 102,
    "XI": 338,
    "XII": 313,
    "XIII": 165,
    "XIV": 126,
    "XV": 6
  },
  "Sònia Farré Fidalgo": {
    "XII": 249
  },
  "Talía Roselló Saus": {
    "X": 428
  },
  "Tania Sánchez Melero": {
    "XI": 241,
    "XII": 272
  },
  "Telmo Martín González": {
    "X": 88
  },
  "Teodoro García Egea": {
    "X": 360,
    "XI": 31,
    "XII": 66,
    "XIII": 349,
    "XIV": 310
  },
  "Teresa Cunillera i Mestres": {
    "X": 185
  },
  "Teresa García Sena": {
    "X": 387
  },
  "Teresa Gomis de Barbarà": {
    "X": 424
  },
  "Teresa Jordà i Roura": {
    "X": 294,
    "XI": 277,
    "XII": 333,
    "XV": 224
  },
  "Teresa Llorens Carbonell": {
    "XV": 22
  },
  "Teresa Palmer Tous": {
    "XII": 228
  },
  "Teresa Ribera Rodríguez": {
    "XIII": 268,
    "XIV": 285,
    "XV": 335
  },
  "Teslem Andala Ubbi": {
    "XV": 338
  },
  "Teófila Martínez Saiz": {
    "X": 25,
    "XI": 35,
    "XII": 164
  },
  "Teófilo de Luis Rodríguez": {
    "X": 81,
    "XI": 149,
    "XII": 82
  },
  "Tomás Burgos Gallego": {
    "X": 270,
    "XI": 173,
    "XII": 113
  },
  "Tomás Cabezón Casas": {
    "XIII": 25,
    "XIV": 28,
    "XV": 2
  },
  "Tomás Fernández Ríos": {
    "XIV": 330,
    "XV": 214
  },
  "Tomás Guitarte Gimeno": {
    "XIV": 306
  },
  "Tomás Javier Fole Díaz": {
    "XII": 357
  },
  "Tomás Valeriano Gómez Sánchez": {
    "X": 161
  },
  "Trinidad Carmen Argota Castro": {
    "XV": 103
  },
  "Trinidad Jiménez García-Herrera": {
    "X": 106
  },
  "Tristana María Moraleja Gómez": {
    "X": 263,
    "XII": 300,
    "XIII": 43,
    "XIV": 57,
    "XV": 198
  },
  "Txema Guijarro García": {
    "XI": 287,
    "XII": 315,
    "XIII": 230,
    "XIV": 344,
    "XV": 92
  },
  "Uxue Barkos Berruezo": {
    "X": 271
  },
  "Uxía Tizón Vázquez": {
    "XIV": 374
  },
  "Valentín García Gómez": {
    "XIII": 151,
    "XIV": 226
  },
  "Valle Mellado Sierra": {
    "XV": 171
  },
  "Verónica Martínez Barbero": {
    "XV": 310
  },
  "Vicent Manuel Sarrià Morell": {
    "XIII": 206,
    "XIV": 90,
    "XV": 219
  },
  "Vicente Betoret Coll": {
    "XIII": 14,
    "XIV": 228
  },
  "Vicente Ferrer Roselló": {
    "X": 277
  },
  "Vicente Guillén Izquierdo": {
    "X": 19
  },
  "Vicente Martínez-Pujalte López": {
    "X": 183
  },
  "Vicente Montávez Aguillaume": {
    "XV": 390
  },
  "Vicente Ten Oliver": {
    "XI": 189,
    "XII": 203,
    "XIII": 140
  },
  "Vicente Tirado Ochoa": {
    "XIII": 187,
    "XIV": 16
  },
  "Vicenç Vidal Matas": {
    "XV": 192
  },
  "Victoria Begoña Tundidor Moreno": {
    "XII": 49
  },
  "Violante Tomás Olivares": {
    "XV": 119
  },
  "Viviane Ogou i Corbi": {
    "XV": 397
  },
  "Víctor Camino Miñana": {
    "XV": 364
  },
  "Víctor González Coello de Portugal": {
    "XIV": 76
  },
  "Víctor Gutiérrez Santiago": {
    "XV": 357
  },
  "Víctor Javier Ruiz de Diego": {
    "XV": 362
  },
  "Víctor Manuel Sánchez del Real": {
    "XIII": 280,
    "XIV": 195
  },
  "Víctor María Calvo-Sotelo Ibáñez-Martín": {
    "X": 60
  },
  "Víctor Morlán Gracia": {
    "X": 201
  },
  "Víctor Valentín Píriz Maya": {
    "XII": 352,
    "XIII": 9,
    "XIV": 9
  },
  "Xabier Mikel Errekondo Saltsamendi": {
    "X": 341
  },
  "Yolanda Díaz Pérez": {
    "XI": 139,
    "XII": 248,
    "XIII": 291,
    "XIV": 171,
    "XV": 342
  },
  "Yolanda Seva Ruiz": {
    "XIII": 184,
    "XIV": 137
  },
  "Zaida Cantera de Castro": {
    "XI": 165,
    "XII": 80,
    "XIII": 48,
    "XIV": 38,
    "XV": 360
  },
  "Àgueda Micó Micó": {
    "XV": 164
  },
  "Àlex Sáez Jubero": {
    "X": 165
  },
  "Àngela Ballester Muñoz": {
    "XI": 283,
    "XII": 220
  },
  "Águeda Fumero Roque": {
    "X": 175
  },
  "Águeda Reynés Calvache": {
    "XI": 267,
    "XII": 229
  },
  "Álvaro Anchuelo Crego": {
    "X": 45
  },
  "Álvaro María Nadal Belda": {
    "X": 62,
    "XI": 261,
    "XII": 287
  },
  "Álvaro Morales Álvarez": {
    "XV": 93
  },
  "Álvaro Pérez López": {
    "XV": 27
  },
  "Álvaro Sanz Remón": {
    "X": 392
  },
  "Ángel Ibáñez Hernando": {
    "XV": 180
  },
  "Ángel Luis González Muñoz": {
    "X": 237,
    "XI": 135,
    "XII": 208,
    "XIV": 391
  },
  "Ángel López Maraver": {
    "XIV": 311,
    "XV": 73
  },
  "Ángela Rodríguez Martínez": {
    "XI": 273,
    "XII": 345
  },
  "Ángeles Isac García": {
    "XI": 244,
    "XII": 190
  },
  "Ángeles Álvarez Álvarez": {
    "X": 99,
    "XII": 102
  },
  "Íñigo Barandiaran Benito": {
    "XI": 118,
    "XII": 231,
    "XIII": 239,
    "XIV": 97
  },
  "Íñigo Errejón Galván": {
    "XI": 223,
    "XII": 185,
    "XIV": 233,
    "XV": 301
  },
  "Íñigo Jesús Alli Martínez": {
    "XI": 71,
    "XII": 211
  },
  "Íñigo Méndez de Vigo Montojo": {
    "XI": 262,
    "XII": 58
  },
  "Óscar Clavell López": {
    "XI": 187,
    "XII": 160,
    "XIII": 195,
    "XIV": 108,
    "XV": 109
  },
  "Óscar Galeano Gracia": {
    "XI": 337,
    "XII": 61
  },
  "Óscar Gamazo Micó": {
    "XII": 289,
    "XIV": 212
  },
  "Óscar López Águeda": {
    "XV": 261
  },
  "Óscar Puente Santiago": {
    "XV": 90
  },
  "Óscar Ramajo Prada": {
    "XV": 46
  }
}